{"title":"Combined feed","url":"https://MusicMagazine.github.io/news/all.xml","elements":[{"title":"베이비몬스터, 일본 TV방송  'SHEESH' 라이브 무대 (KBS연예 ─ 음악)","contents":"<a href=\"https://kstar.kbs.co.kr/list_view.html?idx=316501\">\t<span class=\"img-box hh\">\n\t\t<span class=\"img-thum\">\n\t\t\t<span class=\"img-center\">\n\t\t\t\t<img src=\"https://entertainimg.kbsmedia.co.kr/cms/uploads/CONTENTS_20240519090039_83e6599d20a67eae384aa8c6a7610fa1.jpg\" alt=\"대체 텍스트\">\n\t\t\t</span>\n\t\t</span>\n\t</span></a>\n\t<span class=\"txt\">\n\t\t<span class=\"max-progtit\"><a href=\"https://kstar.kbs.co.kr/list_view.html?idx=316501\">베이비몬스터, 일본 TV방송  'SHEESH' 라이브 무대</a></span>\n\t</span>","link":"https://kstar.kbs.co.kr/list_view.html?idx=316501","retrieved":1716080473170,"image":"https://entertainimg.kbsmedia.co.kr/cms/uploads/CONTENTS_20240519090039_83e6599d20a67eae384aa8c6a7610fa1.jpg"},{"title":"멕시코로 간 라이즈,  ‘테카테 엠블레마’ 페스티벌 & 팬콘 성황! (KBS연예 ─ 음악)","contents":"<a href=\"https://kstar.kbs.co.kr/list_view.html?idx=316477\">\t<span class=\"img-box hh\">\n\t\t<span class=\"img-thum\">\n\t\t\t<span class=\"img-center\">\n\t\t\t\t<img src=\"https://entertainimg.kbsmedia.co.kr/cms/uploads/CONTENTS_20240519080158_6310cde7339b28e7f54332f7eff3a965.jpg\" alt=\"대체 텍스트\">\n\t\t\t</span>\n\t\t</span>\n\t</span></a>\n\t<span class=\"txt\">\n\t\t<span class=\"max-progtit\"><a href=\"https://kstar.kbs.co.kr/list_view.html?idx=316477\">멕시코로 간 라이즈,  ‘테카테 엠블레마’ 페스티벌 &amp; 팬콘 성황!</a></span>\n\t</span>","link":"https://kstar.kbs.co.kr/list_view.html?idx=316477","retrieved":1716073925291,"image":"https://entertainimg.kbsmedia.co.kr/cms/uploads/CONTENTS_20240519080158_6310cde7339b28e7f54332f7eff3a965.jpg"},{"title":"인피니트, 7년만에 '무한대집회' 개최...6월 9일 신곡 발매 (KBS연예 ─ 음악)","contents":"<a href=\"https://kstar.kbs.co.kr/list_view.html?idx=316090\">\t<span class=\"img-box hh\">\n\t\t<span class=\"img-thum\">\n\t\t\t<span class=\"img-center\">\n\t\t\t\t<img src=\"https://entertainimg.kbsmedia.co.kr/cms/uploads/CONTENTS_20240517074239_25bc24963896a183125cb98ecc2753e0.jpg\" alt=\"대체 텍스트\">\n\t\t\t</span>\n\t\t</span>\n\t</span></a>\n\t<span class=\"txt\">\n\t\t<span class=\"max-progtit\"><a href=\"https://kstar.kbs.co.kr/list_view.html?idx=316090\">인피니트, 7년만에 '무한대집회' 개최...6월 9일 신곡 발매</a></span>\n\t</span>","link":"https://kstar.kbs.co.kr/list_view.html?idx=316090","retrieved":1715984065672,"image":"https://entertainimg.kbsmedia.co.kr/cms/uploads/CONTENTS_20240517074239_25bc24963896a183125cb98ecc2753e0.jpg"},{"title":"버추얼 걸그룹 '핑크버스', 'Call Devil’ 30일 발매 (KBS연예 ─ 음악)","contents":"<a href=\"https://kstar.kbs.co.kr/list_view.html?idx=316205\">\t<span class=\"img-box ww\">\n\t\t<span class=\"img-thum\">\n\t\t\t<span class=\"img-center\">\n\t\t\t\t<img src=\"https://entertainimg.kbsmedia.co.kr/cms/uploads/CONTENTS_20240517100020_5cdda0f391ded1b8ad2e6fad124541ac.png\" alt=\"대체 텍스트\">\n\t\t\t</span>\n\t\t</span>\n\t</span></a>\n\t<span class=\"txt\">\n\t\t<span class=\"max-progtit\"><a href=\"https://kstar.kbs.co.kr/list_view.html?idx=316205\">버추얼 걸그룹 '핑크버스', 'Call Devil’ 30일 발매</a></span>\n\t</span>","link":"https://kstar.kbs.co.kr/list_view.html?idx=316205","retrieved":1715910967501,"image":"https://entertainimg.kbsmedia.co.kr/cms/uploads/CONTENTS_20240517100020_5cdda0f391ded1b8ad2e6fad124541ac.png"},{"title":"걸그룹 '아르테미스', 단체 콘셉트 포트.. 31일 정규앨범 'Dall' (KBS연예 ─ 음악)","contents":"<a href=\"https://kstar.kbs.co.kr/list_view.html?idx=316097\">\t<span class=\"img-box hh\">\n\t\t<span class=\"img-thum\">\n\t\t\t<span class=\"img-center\">\n\t\t\t\t<img src=\"https://entertainimg.kbsmedia.co.kr/cms/uploads/CONTENTS_20240517074826_552ff4410c1a2d0c020cdc33f2f570a4_1.jpg\" alt=\"대체 텍스트\">\n\t\t\t</span>\n\t\t</span>\n\t</span></a>\n\t<span class=\"txt\">\n\t\t<span class=\"max-progtit\"><a href=\"https://kstar.kbs.co.kr/list_view.html?idx=316097\">걸그룹 '아르테미스', 단체 콘셉트 포트.. 31일 정규앨범 'Dall'</a></span>\n\t</span>","link":"https://kstar.kbs.co.kr/list_view.html?idx=316097","retrieved":1715901200266,"image":"https://entertainimg.kbsmedia.co.kr/cms/uploads/CONTENTS_20240517074826_552ff4410c1a2d0c020cdc33f2f570a4_1.jpg"},{"title":"뉴진스,일본 도쿄돔 팬미팅 전석 매진 (KBS연예 ─ 음악)","contents":"<a href=\"https://kstar.kbs.co.kr/list_view.html?idx=315660\">\t<span class=\"img-box hh\">\n\t\t<span class=\"img-thum\">\n\t\t\t<span class=\"img-center\">\n\t\t\t\t<img src=\"https://entertainimg.kbsmedia.co.kr/cms/uploads/CONTENTS_20240514081434_824831968cff0bd2c1cd8215f05169f4.jpg\" alt=\"대체 텍스트\">\n\t\t\t</span>\n\t\t</span>\n\t</span></a>\n\t<span class=\"txt\">\n\t\t<span class=\"max-progtit\"><a href=\"https://kstar.kbs.co.kr/list_view.html?idx=315660\">뉴진스,일본 도쿄돔 팬미팅 전석 매진</a></span>\n\t</span>","link":"https://kstar.kbs.co.kr/list_view.html?idx=315660","retrieved":1715648070633,"image":"https://entertainimg.kbsmedia.co.kr/cms/uploads/CONTENTS_20240514081434_824831968cff0bd2c1cd8215f05169f4.jpg"},{"title":"에스파, ‘Supernova’ MV 티저..  다중우주 세계관 ‘초인적’ 매력 예고 (KBS연예 ─ 음악)","contents":"<a href=\"https://kstar.kbs.co.kr/list_view.html?idx=315543\">\t<span class=\"img-box ww\">\n\t\t<span class=\"img-thum\">\n\t\t\t<span class=\"img-center\">\n\t\t\t\t<img src=\"https://entertainimg.kbsmedia.co.kr/cms/uploads/CONTENTS_20240513075829_e6038d25392a78c1773888a0169b595a.png\" alt=\"대체 텍스트\">\n\t\t\t</span>\n\t\t</span>\n\t</span></a>\n\t<span class=\"txt\">\n\t\t<span class=\"max-progtit\"><a href=\"https://kstar.kbs.co.kr/list_view.html?idx=315543\">에스파, ‘Supernova’ MV 티저..  다중우주 세계관 ‘초인적’ 매력 예고</a></span>\n\t</span>","link":"https://kstar.kbs.co.kr/list_view.html?idx=315543","retrieved":1715555663402,"image":"https://entertainimg.kbsmedia.co.kr/cms/uploads/CONTENTS_20240513075829_e6038d25392a78c1773888a0169b595a.png"},{"title":"RM, 선공개 곡 ‘Come back to me’ MV … \"영화적 상상력+감각적인 영상미\" (KBS연예 ─ 음악)","contents":"<a href=\"https://kstar.kbs.co.kr/list_view.html?idx=315235\">\t<span class=\"img-box ww\">\n\t\t<span class=\"img-thum\">\n\t\t\t<span class=\"img-center\">\n\t\t\t\t<img src=\"https://entertainimg.kbsmedia.co.kr/cms/uploads/CONTENTS_20240510173040_98954d525630c64f11eb3498068c203f.png\" alt=\"대체 텍스트\">\n\t\t\t</span>\n\t\t</span>\n\t</span></a>\n\t<span class=\"txt\">\n\t\t<span class=\"max-progtit\"><a href=\"https://kstar.kbs.co.kr/list_view.html?idx=315235\">RM, 선공개 곡 ‘Come back to me’ MV … \"영화적 상상력+감각적인 영상미\"</a></span>\n\t</span>","link":"https://kstar.kbs.co.kr/list_view.html?idx=315235","retrieved":1715332514071,"image":"https://entertainimg.kbsmedia.co.kr/cms/uploads/CONTENTS_20240510173040_98954d525630c64f11eb3498068c203f.png"},{"title":"육성재 컴백.. 싱글앨범 'EXHIBITION : Look Closely' 9일 발매 (KBS연예 ─ 음악)","contents":"<a href=\"https://kstar.kbs.co.kr/list_view.html?idx=314473\">\t<span class=\"img-box hh\">\n\t\t<span class=\"img-thum\">\n\t\t\t<span class=\"img-center\">\n\t\t\t\t<img src=\"https://entertainimg.kbsmedia.co.kr/cms/uploads/CONTENTS_20240504082903_cb412038d84cbab2347bbfdd872c2984.jpg\" alt=\"대체 텍스트\">\n\t\t\t</span>\n\t\t</span>\n\t</span></a>\n\t<span class=\"txt\">\n\t\t<span class=\"max-progtit\"><a href=\"https://kstar.kbs.co.kr/list_view.html?idx=314473\">육성재 컴백.. 싱글앨범 'EXHIBITION : Look Closely' 9일 발매</a></span>\n\t</span>","link":"https://kstar.kbs.co.kr/list_view.html?idx=314473","retrieved":1714864535904,"image":"https://entertainimg.kbsmedia.co.kr/cms/uploads/CONTENTS_20240504082903_cb412038d84cbab2347bbfdd872c2984.jpg"},{"title":"김호중 티켓 파워, ‘월드 유니온 오케스트라 슈퍼클래식’ 완전매진 (KBS연예 ─ 음악)","contents":"<a href=\"https://kstar.kbs.co.kr/list_view.html?idx=314482\">\t<span class=\"img-box hh\">\n\t\t<span class=\"img-thum\">\n\t\t\t<span class=\"img-center\">\n\t\t\t\t<img src=\"https://entertainimg.kbsmedia.co.kr/cms/uploads/CONTENTS_20240504083456_95c4e646d46e2902e1e8ceb632e2c2a8_1.jpg\" alt=\"대체 텍스트\">\n\t\t\t</span>\n\t\t</span>\n\t</span></a>\n\t<span class=\"txt\">\n\t\t<span class=\"max-progtit\"><a href=\"https://kstar.kbs.co.kr/list_view.html?idx=314482\">김호중 티켓 파워, ‘월드 유니온 오케스트라 슈퍼클래식’ 완전매진</a></span>\n\t</span>","link":"https://kstar.kbs.co.kr/list_view.html?idx=314482","retrieved":1714784073368,"image":"https://entertainimg.kbsmedia.co.kr/cms/uploads/CONTENTS_20240504083456_95c4e646d46e2902e1e8ceb632e2c2a8_1.jpg"},{"title":"김재환, 미니 7집 'I Adore' 라이브 버전 하이라이트 메들리 공개 (KBS연예 ─ 음악)","contents":"<a href=\"https://kstar.kbs.co.kr/list_view.html?idx=314294\">\t<span class=\"img-box hh\">\n\t\t<span class=\"img-thum\">\n\t\t\t<span class=\"img-center\">\n\t\t\t\t<img src=\"https://entertainimg.kbsmedia.co.kr/cms/uploads/CONTENTS_20240503083630_6fb8d6e7fcb8d2a98567a24fb22dc7c4_1.png\" alt=\"대체 텍스트\">\n\t\t\t</span>\n\t\t</span>\n\t</span></a>\n\t<span class=\"txt\">\n\t\t<span class=\"max-progtit\"><a href=\"https://kstar.kbs.co.kr/list_view.html?idx=314294\">김재환, 미니 7집 'I Adore' 라이브 버전 하이라이트 메들리 공개</a></span>\n\t</span>","link":"https://kstar.kbs.co.kr/list_view.html?idx=314294","retrieved":1714774615604,"image":"https://entertainimg.kbsmedia.co.kr/cms/uploads/CONTENTS_20240503083630_6fb8d6e7fcb8d2a98567a24fb22dc7c4_1.png"},{"title":"RM, 솔로 2집 콘셉트포토.. 일본 신진 사진가와 협업 (KBS연예 ─ 음악)","contents":"<a href=\"https://kstar.kbs.co.kr/list_view.html?idx=314305\">\t<span class=\"img-box ww\">\n\t\t<span class=\"img-thum\">\n\t\t\t<span class=\"img-center\">\n\t\t\t\t<img src=\"https://entertainimg.kbsmedia.co.kr/cms/uploads/CONTENTS_20240503090332_1f33770238ddec4445e1e51ce85d1786.jpg\" alt=\"대체 텍스트\">\n\t\t\t</span>\n\t\t</span>\n\t</span></a>\n\t<span class=\"txt\">\n\t\t<span class=\"max-progtit\"><a href=\"https://kstar.kbs.co.kr/list_view.html?idx=314305\">RM, 솔로 2집 콘셉트포토.. 일본 신진 사진가와 협업</a></span>\n\t</span>","link":"https://kstar.kbs.co.kr/list_view.html?idx=314305","retrieved":1714697728756,"image":"https://entertainimg.kbsmedia.co.kr/cms/uploads/CONTENTS_20240503090332_1f33770238ddec4445e1e51ce85d1786.jpg"},{"title":"7월의 트와이스, 일본 정규5집 'DIVE' 발매 (KBS연예 ─ 음악)","contents":"<a href=\"https://kstar.kbs.co.kr/list_view.html?idx=314212\">\t<span class=\"img-box hh\">\n\t\t<span class=\"img-thum\">\n\t\t\t<span class=\"img-center\">\n\t\t\t\t<img src=\"https://entertainimg.kbsmedia.co.kr/cms/uploads/CONTENTS_20240502155732_2daa8e1bf6baa57d5ca2caabbed2fa84_1.jpg\" alt=\"대체 텍스트\">\n\t\t\t</span>\n\t\t</span>\n\t</span></a>\n\t<span class=\"txt\">\n\t\t<span class=\"max-progtit\"><a href=\"https://kstar.kbs.co.kr/list_view.html?idx=314212\">7월의 트와이스, 일본 정규5집 'DIVE' 발매</a></span>\n\t</span>","link":"https://kstar.kbs.co.kr/list_view.html?idx=314212","retrieved":1714634188069,"image":"https://entertainimg.kbsmedia.co.kr/cms/uploads/CONTENTS_20240502155732_2daa8e1bf6baa57d5ca2caabbed2fa84_1.jpg"},{"title":"휘브(WHIB) 14일 컴백.. \"하나의 꿈을 위해 뭉친 여덟 청춘!\" (KBS연예 ─ 음악)","contents":"<a href=\"https://kstar.kbs.co.kr/list_view.html?idx=314146\">\t<span class=\"img-box hh\">\n\t\t<span class=\"img-thum\">\n\t\t\t<span class=\"img-center\">\n\t\t\t\t<img src=\"https://entertainimg.kbsmedia.co.kr/cms/uploads/CONTENTS_20240502091312_7be210dedb67fef321aa201ed00037b7.jpg\" alt=\"대체 텍스트\">\n\t\t\t</span>\n\t\t</span>\n\t</span></a>\n\t<span class=\"txt\">\n\t\t<span class=\"max-progtit\"><a href=\"https://kstar.kbs.co.kr/list_view.html?idx=314146\">휘브(WHIB) 14일 컴백.. \"하나의 꿈을 위해 뭉친 여덟 청춘!\"</a></span>\n\t</span>","link":"https://kstar.kbs.co.kr/list_view.html?idx=314146","retrieved":1714611144992,"image":"https://entertainimg.kbsmedia.co.kr/cms/uploads/CONTENTS_20240502091312_7be210dedb67fef321aa201ed00037b7.jpg"},{"title":"ZEROBASEONE, 'You had me at HELLO' 콘셉트 포토.. 'SOLAR' 버전 (KBS연예 ─ 음악)","contents":"<a href=\"https://kstar.kbs.co.kr/list_view.html?idx=314124\">\t<span class=\"img-box hh\">\n\t\t<span class=\"img-thum\">\n\t\t\t<span class=\"img-center\">\n\t\t\t\t<img src=\"https://entertainimg.kbsmedia.co.kr/cms/uploads/CONTENTS_20240502081933_6c9c572a82f87b0dfe79a8eb1ebfd3ff.jpg\" alt=\"대체 텍스트\">\n\t\t\t</span>\n\t\t</span>\n\t</span></a>\n\t<span class=\"txt\">\n\t\t<span class=\"max-progtit\"><a href=\"https://kstar.kbs.co.kr/list_view.html?idx=314124\">ZEROBASEONE, 'You had me at HELLO' 콘셉트 포토.. 'SOLAR' 버전 </a></span>\n\t</span>","link":"https://kstar.kbs.co.kr/list_view.html?idx=314124","retrieved":1714611144994,"image":"https://entertainimg.kbsmedia.co.kr/cms/uploads/CONTENTS_20240502081933_6c9c572a82f87b0dfe79a8eb1ebfd3ff.jpg"},{"title":"\"뉴진스, 파워퍼프걸!\"..  6월 일본 데뷔 싱글, 무라카미 다카시와 컬래버 (KBS연예 ─ 음악)","contents":"<a href=\"https://kstar.kbs.co.kr/list_view.html?idx=314034\">\t<span class=\"img-box ww\">\n\t\t<span class=\"img-thum\">\n\t\t\t<span class=\"img-center\">\n\t\t\t\t<img src=\"https://entertainimg.kbsmedia.co.kr/cms/uploads/CONTENTS_20240501104543_641a26f01fc42f3ca9df7efcea36cb23.jpg\" alt=\"대체 텍스트\">\n\t\t\t</span>\n\t\t</span>\n\t</span></a>\n\t<span class=\"txt\">\n\t\t<span class=\"max-progtit\"><a href=\"https://kstar.kbs.co.kr/list_view.html?idx=314034\">\"뉴진스, 파워퍼프걸!\"..  6월 일본 데뷔 싱글, 무라카미 다카시와 컬래버</a></span>\n\t</span>","link":"https://kstar.kbs.co.kr/list_view.html?idx=314034","retrieved":1714528785057,"image":"https://entertainimg.kbsmedia.co.kr/cms/uploads/CONTENTS_20240501104543_641a26f01fc42f3ca9df7efcea36cb23.jpg"},{"title":"김재환, 5월 컴백... 미니 7집 'I Adore' (KBS연예 ─ 음악)","contents":"<a href=\"https://kstar.kbs.co.kr/list_view.html?idx=313757\">\t<span class=\"img-box hh\">\n\t\t<span class=\"img-thum\">\n\t\t\t<span class=\"img-center\">\n\t\t\t\t<img src=\"https://entertainimg.kbsmedia.co.kr/cms/uploads/CONTENTS_20240429085702_4fde7860b82ef09b913ac7fae0a4091c.jpg\" alt=\"대체 텍스트\">\n\t\t\t</span>\n\t\t</span>\n\t</span></a>\n\t<span class=\"txt\">\n\t\t<span class=\"max-progtit\"><a href=\"https://kstar.kbs.co.kr/list_view.html?idx=313757\">김재환, 5월 컴백... 미니 7집 'I Adore'</a></span>\n\t</span>","link":"https://kstar.kbs.co.kr/list_view.html?idx=313757","retrieved":1714457861773,"image":"https://entertainimg.kbsmedia.co.kr/cms/uploads/CONTENTS_20240429085702_4fde7860b82ef09b913ac7fae0a4091c.jpg"},{"title":"아이유, 자카르타 공연 성료..  \"홍콩 , 마닐라...  월드투어는 계속된다\" (KBS연예 ─ 음악)","contents":"<a href=\"https://kstar.kbs.co.kr/list_view.html?idx=313743\">\t<span class=\"img-box hh\">\n\t\t<span class=\"img-thum\">\n\t\t\t<span class=\"img-center\">\n\t\t\t\t<img src=\"https://entertainimg.kbsmedia.co.kr/cms/uploads/CONTENTS_20240429082242_3d7c84a156e99d4d1f1012b1fdcec0c8.jpg\" alt=\"대체 텍스트\">\n\t\t\t</span>\n\t\t</span>\n\t</span></a>\n\t<span class=\"txt\">\n\t\t<span class=\"max-progtit\"><a href=\"https://kstar.kbs.co.kr/list_view.html?idx=313743\">아이유, 자카르타 공연 성료..  \"홍콩 , 마닐라...  월드투어는 계속된다\" </a></span>\n\t</span>","link":"https://kstar.kbs.co.kr/list_view.html?idx=313743","retrieved":1714352020740,"image":"https://entertainimg.kbsmedia.co.kr/cms/uploads/CONTENTS_20240429082242_3d7c84a156e99d4d1f1012b1fdcec0c8.jpg"},{"title":"82메이저 컴백, 첫 미니앨범  'BEAT by 82' (KBS연예 ─ 음악)","contents":"<a href=\"https://kstar.kbs.co.kr/list_view.html?idx=313707\">\t<span class=\"img-box hh\">\n\t\t<span class=\"img-thum\">\n\t\t\t<span class=\"img-center\">\n\t\t\t\t<img src=\"https://entertainimg.kbsmedia.co.kr/cms/uploads/CONTENTS_20240429074438_3c9b5f7151dfe48b56fbfbfd2b2709f8.jpg\" alt=\"대체 텍스트\">\n\t\t\t</span>\n\t\t</span>\n\t</span></a>\n\t<span class=\"txt\">\n\t\t<span class=\"max-progtit\"><a href=\"https://kstar.kbs.co.kr/list_view.html?idx=313707\">82메이저 컴백, 첫 미니앨범  'BEAT by 82'</a></span>\n\t</span>","link":"https://kstar.kbs.co.kr/list_view.html?idx=313707","retrieved":1714345861947,"image":"https://entertainimg.kbsmedia.co.kr/cms/uploads/CONTENTS_20240429074438_3c9b5f7151dfe48b56fbfbfd2b2709f8.jpg"},{"title":"뉴진스, 논란 속 신곡 ‘Bubble Gum’ 뮤직비디오 선공개 (KBS연예 ─ 음악)","contents":"<a href=\"https://kstar.kbs.co.kr/list_view.html?idx=313621\">\t<span class=\"img-box hh\">\n\t\t<span class=\"img-thum\">\n\t\t\t<span class=\"img-center\">\n\t\t\t\t<img src=\"https://entertainimg.kbsmedia.co.kr/cms/uploads/CONTENTS_20240428072259_4067d4d7dfa5adfb9fe13c670da88910.png\" alt=\"대체 텍스트\">\n\t\t\t</span>\n\t\t</span>\n\t</span></a>\n\t<span class=\"txt\">\n\t\t<span class=\"max-progtit\"><a href=\"https://kstar.kbs.co.kr/list_view.html?idx=313621\">뉴진스, 논란 속 신곡 ‘Bubble Gum’ 뮤직비디오 선공개</a></span>\n\t</span>","link":"https://kstar.kbs.co.kr/list_view.html?idx=313621","retrieved":1714259534611,"image":"https://entertainimg.kbsmedia.co.kr/cms/uploads/CONTENTS_20240428072259_4067d4d7dfa5adfb9fe13c670da88910.png"},{"title":"김호중 음주운전 등 사실관계  인정.. \"경찰 조사에 성실히 임하겠습니다\" (KBS연예 ─ 연예)","contents":"<a href=\"https://kstar.kbs.co.kr/list_view.html?idx=316531\">\t<span class=\"img-box hh\">\n\t\t<span class=\"img-thum\">\n\t\t\t<span class=\"img-center\">\n\t\t\t\t<img src=\"https://entertainimg.kbsmedia.co.kr/cms/uploads/CONTENTS_20240519222419_b87f9e699b4814e96156f6e4b7cad937.jpg\" alt=\"대체 텍스트\">\n\t\t\t</span>\n\t\t</span>\n\t</span></a>\n\t<span class=\"txt\">\n\t\t<span class=\"max-progtit\"><a href=\"https://kstar.kbs.co.kr/list_view.html?idx=316531\"> 김호중 음주운전 등 사실관계  인정.. \"경찰 조사에 성실히 임하겠습니다\" </a></span>\n\t</span>","link":"https://kstar.kbs.co.kr/list_view.html?idx=316531","retrieved":1716127885377,"image":"https://entertainimg.kbsmedia.co.kr/cms/uploads/CONTENTS_20240519222419_b87f9e699b4814e96156f6e4b7cad937.jpg"},{"title":"베키 체임버스 연작 '수도승과 로봇' 시리즈 출간... 솔라 펑크 장르 최고봉 (KBS연예 ─ 연예)","contents":"<a href=\"https://kstar.kbs.co.kr/list_view.html?idx=316488\">\t<span class=\"img-box hh\">\n\t\t<span class=\"img-thum\">\n\t\t\t<span class=\"img-center\">\n\t\t\t\t<img src=\"https://entertainimg.kbsmedia.co.kr/cms/uploads/CONTENTS_20240519082000_698f7c0fdc3a79706b76e3278f3a25b0.jpg\" alt=\"대체 텍스트\">\n\t\t\t</span>\n\t\t</span>\n\t</span></a>\n\t<span class=\"txt\">\n\t\t<span class=\"max-progtit\"><a href=\"https://kstar.kbs.co.kr/list_view.html?idx=316488\">베키 체임버스 연작 '수도승과 로봇' 시리즈 출간... 솔라 펑크 장르 최고봉</a></span>\n\t</span>","link":"https://kstar.kbs.co.kr/list_view.html?idx=316488","retrieved":1716080482305,"image":"https://entertainimg.kbsmedia.co.kr/cms/uploads/CONTENTS_20240519082000_698f7c0fdc3a79706b76e3278f3a25b0.jpg"},{"title":"뮤지컬 '이블데드' 6월 개막...  \"올여름, 좀비들이 돌아온다!\" (KBS연예 ─ 연예)","contents":"<a href=\"https://kstar.kbs.co.kr/list_view.html?idx=316015\">\t<span class=\"img-box hh\">\n\t\t<span class=\"img-thum\">\n\t\t\t<span class=\"img-center\">\n\t\t\t\t<img src=\"https://entertainimg.kbsmedia.co.kr/cms/uploads/CONTENTS_20240516110646_e69fa3b80bb7cc5ef6ff57ca6dcd1bb8.jpg\" alt=\"대체 텍스트\">\n\t\t\t</span>\n\t\t</span>\n\t</span></a>\n\t<span class=\"txt\">\n\t\t<span class=\"max-progtit\"><a href=\"https://kstar.kbs.co.kr/list_view.html?idx=316015\">뮤지컬 '이블데드' 6월 개막...  \"올여름, 좀비들이 돌아온다!\"</a></span>\n\t</span>","link":"https://kstar.kbs.co.kr/list_view.html?idx=316015","retrieved":1716073933046,"image":"https://entertainimg.kbsmedia.co.kr/cms/uploads/CONTENTS_20240516110646_e69fa3b80bb7cc5ef6ff57ca6dcd1bb8.jpg"},{"title":"안소희 연극 데뷔, '클로저.. 솔직하고 감각적인 앨리스 변신 (KBS연예 ─ 연예)","contents":"<a href=\"https://kstar.kbs.co.kr/list_view.html?idx=316326\">\t<span class=\"img-box hh\">\n\t\t<span class=\"img-thum\">\n\t\t\t<span class=\"img-center\">\n\t\t\t\t<img src=\"https://entertainimg.kbsmedia.co.kr/cms/uploads/CONTENTS_20240518061608_583fe176ab1a4d3c38fe18a75361a7c3.jpg\" alt=\"대체 텍스트\">\n\t\t\t</span>\n\t\t</span>\n\t</span></a>\n\t<span class=\"txt\">\n\t\t<span class=\"max-progtit\"><a href=\"https://kstar.kbs.co.kr/list_view.html?idx=316326\">안소희 연극 데뷔, '클로저.. 솔직하고 감각적인 앨리스 변신</a></span>\n\t</span>","link":"https://kstar.kbs.co.kr/list_view.html?idx=316326","retrieved":1715984072743,"image":"https://entertainimg.kbsmedia.co.kr/cms/uploads/CONTENTS_20240518061608_583fe176ab1a4d3c38fe18a75361a7c3.jpg"},{"title":"피아니스트 백건우, 첫 모차르트 앨범 선보인다 (KBS연예 ─ 연예)","contents":"<a href=\"https://kstar.kbs.co.kr/list_view.html?idx=316221\">\t<span class=\"img-box hh\">\n\t\t<span class=\"img-thum\">\n\t\t\t<span class=\"img-center\">\n\t\t\t\t<img src=\"https://entertainimg.kbsmedia.co.kr/cms/uploads/CONTENTS_20240517101102_e25c47d4a9b735d93c4cb17deaf32d53.jpg\" alt=\"대체 텍스트\">\n\t\t\t</span>\n\t\t</span>\n\t</span></a>\n\t<span class=\"txt\">\n\t\t<span class=\"max-progtit\"><a href=\"https://kstar.kbs.co.kr/list_view.html?idx=316221\">피아니스트 백건우, 첫 모차르트 앨범 선보인다</a></span>\n\t</span>","link":"https://kstar.kbs.co.kr/list_view.html?idx=316221","retrieved":1715910973787,"image":"https://entertainimg.kbsmedia.co.kr/cms/uploads/CONTENTS_20240517101102_e25c47d4a9b735d93c4cb17deaf32d53.jpg"},{"title":"카카오엔터 ‘레벨업 못하는 플레이어’ 액션 게임으로 재탄생 (KBS연예 ─ 연예)","contents":"<a href=\"https://kstar.kbs.co.kr/list_view.html?idx=315987\">\t<span class=\"img-box hh\">\n\t\t<span class=\"img-thum\">\n\t\t\t<span class=\"img-center\">\n\t\t\t\t<img src=\"https://entertainimg.kbsmedia.co.kr/cms/uploads/CONTENTS_20240516085154_1ed9091b539f9420055404f06d72022e.jpg\" alt=\"대체 텍스트\">\n\t\t\t</span>\n\t\t</span>\n\t</span></a>\n\t<span class=\"txt\">\n\t\t<span class=\"max-progtit\"><a href=\"https://kstar.kbs.co.kr/list_view.html?idx=315987\">카카오엔터 ‘레벨업 못하는 플레이어’ 액션 게임으로 재탄생</a></span>\n\t</span>","link":"https://kstar.kbs.co.kr/list_view.html?idx=315987","retrieved":1715821095395,"image":"https://entertainimg.kbsmedia.co.kr/cms/uploads/CONTENTS_20240516085154_1ed9091b539f9420055404f06d72022e.jpg"},{"title":"리디, 웹툰 '품격을 배반한다'... 일본 거래액 10억원 돌파 (KBS연예 ─ 연예)","contents":"<a href=\"https://kstar.kbs.co.kr/list_view.html?idx=315982\">\t<span class=\"img-box hh\">\n\t\t<span class=\"img-thum\">\n\t\t\t<span class=\"img-center\">\n\t\t\t\t<img src=\"https://entertainimg.kbsmedia.co.kr/cms/uploads/CONTENTS_20240516084643_0cd6a100b8e18fe423cf1ee974261e6c.jpg\" alt=\"대체 텍스트\">\n\t\t\t</span>\n\t\t</span>\n\t</span></a>\n\t<span class=\"txt\">\n\t\t<span class=\"max-progtit\"><a href=\"https://kstar.kbs.co.kr/list_view.html?idx=315982\">리디, 웹툰 '품격을 배반한다'... 일본 거래액 10억원 돌파</a></span>\n\t</span>","link":"https://kstar.kbs.co.kr/list_view.html?idx=315982","retrieved":1715821095398,"image":"https://entertainimg.kbsmedia.co.kr/cms/uploads/CONTENTS_20240516084643_0cd6a100b8e18fe423cf1ee974261e6c.jpg"},{"title":"뮤지컬 ‘베르사유의 장미’.. 티저 영상 공개..\"살고 싶은 세상을 위해!\" (KBS연예 ─ 연예)","contents":"<a href=\"https://kstar.kbs.co.kr/list_view.html?idx=315951\">\t<span class=\"img-box ww\">\n\t\t<span class=\"img-thum\">\n\t\t\t<span class=\"img-center\">\n\t\t\t\t<img src=\"https://entertainimg.kbsmedia.co.kr/cms/uploads/CONTENTS_20240516074914_c4d1434045f83411d9ecafd84a3e787c.png\" alt=\"대체 텍스트\">\n\t\t\t</span>\n\t\t</span>\n\t</span></a>\n\t<span class=\"txt\">\n\t\t<span class=\"max-progtit\"><a href=\"https://kstar.kbs.co.kr/list_view.html?idx=315951\">뮤지컬 ‘베르사유의 장미’.. 티저 영상 공개..\"살고 싶은 세상을 위해!\"</a></span>\n\t</span>","link":"https://kstar.kbs.co.kr/list_view.html?idx=315951","retrieved":1715821095402,"image":"https://entertainimg.kbsmedia.co.kr/cms/uploads/CONTENTS_20240516074914_c4d1434045f83411d9ecafd84a3e787c.png"},{"title":"\"이거, 바꿔!\".. 미타니 코키 대표작 '웃음의 대학' 광화문에서 펼쳐진다 (KBS연예 ─ 연예)","contents":"<a href=\"https://kstar.kbs.co.kr/list_view.html?idx=315864\">\t<span class=\"img-box hh\">\n\t\t<span class=\"img-thum\">\n\t\t\t<span class=\"img-center\">\n\t\t\t\t<img src=\"https://entertainimg.kbsmedia.co.kr/cms/uploads/CONTENTS_20240515152709_baf7001adfa07235e9d3bd829989c267.jpg\" alt=\"대체 텍스트\">\n\t\t\t</span>\n\t\t</span>\n\t</span></a>\n\t<span class=\"txt\">\n\t\t<span class=\"max-progtit\"><a href=\"https://kstar.kbs.co.kr/list_view.html?idx=315864\">\"이거, 바꿔!\".. 미타니 코키 대표작 '웃음의 대학' 광화문에서 펼쳐진다</a></span>\n\t</span>","link":"https://kstar.kbs.co.kr/list_view.html?idx=315864","retrieved":1715757166754,"image":"https://entertainimg.kbsmedia.co.kr/cms/uploads/CONTENTS_20240515152709_baf7001adfa07235e9d3bd829989c267.jpg"},{"title":"황정민의 맥베스, 요시다 유니의 감각.. '맥베스' 콜라보 포스터 공개 (KBS연예 ─ 연예)","contents":"<a href=\"https://kstar.kbs.co.kr/list_view.html?idx=315686\">\t<span class=\"img-box hh\">\n\t\t<span class=\"img-thum\">\n\t\t\t<span class=\"img-center\">\n\t\t\t\t<img src=\"https://entertainimg.kbsmedia.co.kr/cms/uploads/CONTENTS_20240514105724_9c7d47a01ab1a42b5102c9b40ac0e75e.jpg\" alt=\"대체 텍스트\">\n\t\t\t</span>\n\t\t</span>\n\t</span></a>\n\t<span class=\"txt\">\n\t\t<span class=\"max-progtit\"><a href=\"https://kstar.kbs.co.kr/list_view.html?idx=315686\">황정민의 맥베스, 요시다 유니의 감각.. '맥베스' 콜라보 포스터 공개</a></span>\n\t</span>","link":"https://kstar.kbs.co.kr/list_view.html?idx=315686","retrieved":1715653594559,"image":"https://entertainimg.kbsmedia.co.kr/cms/uploads/CONTENTS_20240514105724_9c7d47a01ab1a42b5102c9b40ac0e75e.jpg"},{"title":"[현장] 황정민의 무대열정, 샘컴퍼니의 ‘맥베스’ 제작발표회 (KBS연예 ─ 연예)","contents":"<a href=\"https://kstar.kbs.co.kr/list_view.html?idx=315314\">\t<span class=\"img-box hh\">\n\t\t<span class=\"img-thum\">\n\t\t\t<span class=\"img-center\">\n\t\t\t\t<img src=\"https://entertainimg.kbsmedia.co.kr/cms/uploads/CONTENTS_20240511100619_18d8d3aed514948c3d8b9da4bde1d7e0.png\" alt=\"대체 텍스트\">\n\t\t\t</span>\n\t\t</span>\n\t</span></a>\n\t<span class=\"txt\">\n\t\t<span class=\"max-progtit\"><a href=\"https://kstar.kbs.co.kr/list_view.html?idx=315314\">[현장] 황정민의 무대열정, 샘컴퍼니의 ‘맥베스’ 제작발표회 </a></span>\n\t</span>","link":"https://kstar.kbs.co.kr/list_view.html?idx=315314","retrieved":1715544814333,"image":"https://entertainimg.kbsmedia.co.kr/cms/uploads/CONTENTS_20240511100619_18d8d3aed514948c3d8b9da4bde1d7e0.png"},{"title":"[전시] “뱅크시, 있다없다 여기있다”..  <리얼 뱅크시> 전시회 (KBS연예 ─ 연예)","contents":"<a href=\"https://kstar.kbs.co.kr/list_view.html?idx=315323\">\t<span class=\"img-box hh\">\n\t\t<span class=\"img-thum\">\n\t\t\t<span class=\"img-center\">\n\t\t\t\t<img src=\"https://entertainimg.kbsmedia.co.kr/cms/uploads/CONTENTS_20240511104154_86dcba8acce15a7a4f4655e3d59ed41f.jpg\" alt=\"대체 텍스트\">\n\t\t\t</span>\n\t\t</span>\n\t</span></a>\n\t<span class=\"txt\">\n\t\t<span class=\"max-progtit\"><a href=\"https://kstar.kbs.co.kr/list_view.html?idx=315323\">[전시] “뱅크시, 있다없다 여기있다”..  &lt;리얼 뱅크시&gt; 전시회</a></span>\n\t</span>","link":"https://kstar.kbs.co.kr/list_view.html?idx=315323","retrieved":1715394242932,"image":"https://entertainimg.kbsmedia.co.kr/cms/uploads/CONTENTS_20240511104154_86dcba8acce15a7a4f4655e3d59ed41f.jpg"},{"title":"뮤지컬 '벤자민 버튼' 11일 개막.. \"김재범·심창민·김성식의 시간은 거꾸로 간다\" (KBS연예 ─ 연예)","contents":"<a href=\"https://kstar.kbs.co.kr/list_view.html?idx=315219\">\t<span class=\"img-box hh\">\n\t\t<span class=\"img-thum\">\n\t\t\t<span class=\"img-center\">\n\t\t\t\t<img src=\"https://entertainimg.kbsmedia.co.kr/cms/uploads/CONTENTS_20240510171442_13f3661d6f07a43cce77be3c8c7b6fef.jpg\" alt=\"대체 텍스트\">\n\t\t\t</span>\n\t\t</span>\n\t</span></a>\n\t<span class=\"txt\">\n\t\t<span class=\"max-progtit\"><a href=\"https://kstar.kbs.co.kr/list_view.html?idx=315219\">뮤지컬 '벤자민 버튼' 11일 개막.. \"김재범·심창민·김성식의 시간은 거꾸로 간다\"</a></span>\n\t</span>","link":"https://kstar.kbs.co.kr/list_view.html?idx=315219","retrieved":1715394242933,"image":"https://entertainimg.kbsmedia.co.kr/cms/uploads/CONTENTS_20240510171442_13f3661d6f07a43cce77be3c8c7b6fef.jpg"},{"title":"6월에 만나는 뮤지컬, '4월은 너의 거짓말’ 캐스팅 공개.. 이홍기·윤소호·김희재·이봄소리·케이·정지소 (KBS연예 ─ 연예)","contents":"<a href=\"https://kstar.kbs.co.kr/list_view.html?idx=314907\">\t<span class=\"img-box hh\">\n\t\t<span class=\"img-thum\">\n\t\t\t<span class=\"img-center\">\n\t\t\t\t<img src=\"https://entertainimg.kbsmedia.co.kr/cms/uploads/CONTENTS_20240508072055_a0186cf89fd7afedd9a6449ab6d0f902.jpg\" alt=\"대체 텍스트\">\n\t\t\t</span>\n\t\t</span>\n\t</span></a>\n\t<span class=\"txt\">\n\t\t<span class=\"max-progtit\"><a href=\"https://kstar.kbs.co.kr/list_view.html?idx=314907\">6월에 만나는 뮤지컬, '4월은 너의 거짓말’ 캐스팅 공개.. 이홍기·윤소호·김희재·이봄소리·케이·정지소</a></span>\n\t</span>","link":"https://kstar.kbs.co.kr/list_view.html?idx=314907","retrieved":1715206265320,"image":"https://entertainimg.kbsmedia.co.kr/cms/uploads/CONTENTS_20240508072055_a0186cf89fd7afedd9a6449ab6d0f902.jpg"},{"title":"제60회 백상예술대상, '무빙'· 김성수 감독 대상... \"시대정신 담은 K-콘텐트의 힘\" (KBS연예 ─ 연예)","contents":"<a href=\"https://kstar.kbs.co.kr/list_view.html?idx=314941\">\t<span class=\"img-box hh\">\n\t\t<span class=\"img-thum\">\n\t\t\t<span class=\"img-center\">\n\t\t\t\t<img src=\"https://entertainimg.kbsmedia.co.kr/cms/uploads/CONTENTS_20240508164149_3f4077ec6cd915cb2ff4254dfb40644f.jpg\" alt=\"대체 텍스트\">\n\t\t\t</span>\n\t\t</span>\n\t</span></a>\n\t<span class=\"txt\">\n\t\t<span class=\"max-progtit\"><a href=\"https://kstar.kbs.co.kr/list_view.html?idx=314941\">제60회 백상예술대상, '무빙'· 김성수 감독 대상... \"시대정신 담은 K-콘텐트의 힘\"</a></span>\n\t</span>","link":"https://kstar.kbs.co.kr/list_view.html?idx=314941","retrieved":1715156040751,"image":"https://entertainimg.kbsmedia.co.kr/cms/uploads/CONTENTS_20240508164149_3f4077ec6cd915cb2ff4254dfb40644f.jpg"},{"title":"뮤지컬 '하데스타운' 7월 개막.. 세상을 구원할 노래 (KBS연예 ─ 연예)","contents":"<a href=\"https://kstar.kbs.co.kr/list_view.html?idx=314449\">\t<span class=\"img-box hh\">\n\t\t<span class=\"img-thum\">\n\t\t\t<span class=\"img-center\">\n\t\t\t\t<img src=\"https://entertainimg.kbsmedia.co.kr/cms/uploads/CONTENTS_20240504080117_ee89c3f819aaeb35bb51925d0aad7168.jpg\" alt=\"대체 텍스트\">\n\t\t\t</span>\n\t\t</span>\n\t</span></a>\n\t<span class=\"txt\">\n\t\t<span class=\"max-progtit\"><a href=\"https://kstar.kbs.co.kr/list_view.html?idx=314449\">뮤지컬 '하데스타운' 7월 개막.. 세상을 구원할 노래</a></span>\n\t</span>","link":"https://kstar.kbs.co.kr/list_view.html?idx=314449","retrieved":1714777945480,"image":"https://entertainimg.kbsmedia.co.kr/cms/uploads/CONTENTS_20240504080117_ee89c3f819aaeb35bb51925d0aad7168.jpg"},{"title":"‘서울 페스타 2024’.. 김영환 관광체육국장 “서울을 프렌들리하게 세계에 알린다” (KBS연예 ─ 연예)","contents":"<a href=\"https://kstar.kbs.co.kr/list_view.html?idx=314397\">\t<span class=\"img-box hh\">\n\t\t<span class=\"img-thum\">\n\t\t\t<span class=\"img-center\">\n\t\t\t\t<img src=\"https://entertainimg.kbsmedia.co.kr/cms/uploads/CONTENTS_20240503155016_709b8a20c7d273a64ca0a67a1c3a3e8e.JPG\" alt=\"대체 텍스트\">\n\t\t\t</span>\n\t\t</span>\n\t</span></a>\n\t<span class=\"txt\">\n\t\t<span class=\"max-progtit\"><a href=\"https://kstar.kbs.co.kr/list_view.html?idx=314397\">‘서울 페스타 2024’.. 김영환 관광체육국장 “서울을 프렌들리하게 세계에 알린다”</a></span>\n\t</span>","link":"https://kstar.kbs.co.kr/list_view.html?idx=314397","retrieved":1714720325803,"image":"https://entertainimg.kbsmedia.co.kr/cms/uploads/CONTENTS_20240503155016_709b8a20c7d273a64ca0a67a1c3a3e8e.JPG"},{"title":"카카오 신작웹툰 론칭.. '폭력의 대가' -'천재 궁수의 스트리밍' (KBS연예 ─ 연예)","contents":"<a href=\"https://kstar.kbs.co.kr/list_view.html?idx=314314\">\t<span class=\"img-box hh\">\n\t\t<span class=\"img-thum\">\n\t\t\t<span class=\"img-center\">\n\t\t\t\t<img src=\"https://entertainimg.kbsmedia.co.kr/cms/uploads/CONTENTS_20240503091409_176a60a47cd0cf6c00f0bc7c19242489.jpg\" alt=\"대체 텍스트\">\n\t\t\t</span>\n\t\t</span>\n\t</span></a>\n\t<span class=\"txt\">\n\t\t<span class=\"max-progtit\"><a href=\"https://kstar.kbs.co.kr/list_view.html?idx=314314\">카카오 신작웹툰 론칭.. '폭력의 대가' -'천재 궁수의 스트리밍'</a></span>\n\t</span>","link":"https://kstar.kbs.co.kr/list_view.html?idx=314314","retrieved":1714697736923,"image":"https://entertainimg.kbsmedia.co.kr/cms/uploads/CONTENTS_20240503091409_176a60a47cd0cf6c00f0bc7c19242489.jpg"},{"title":"재즈 보컬리스트 Moon(혜원), 츠요시 야마모토 트리오와 컬래버레이션 앨범 (KBS연예 ─ 연예)","contents":"<a href=\"https://kstar.kbs.co.kr/list_view.html?idx=314299\">\t<span class=\"img-box hh\">\n\t\t<span class=\"img-thum\">\n\t\t\t<span class=\"img-center\">\n\t\t\t\t<img src=\"https://entertainimg.kbsmedia.co.kr/cms/uploads/CONTENTS_20240503084110_bb69c0bbf90be8ce2f2fe6635374b484.jpg\" alt=\"대체 텍스트\">\n\t\t\t</span>\n\t\t</span>\n\t</span></a>\n\t<span class=\"txt\">\n\t\t<span class=\"max-progtit\"><a href=\"https://kstar.kbs.co.kr/list_view.html?idx=314299\">재즈 보컬리스트 Moon(혜원), 츠요시 야마모토 트리오와 컬래버레이션 앨범 </a></span>\n\t</span>","link":"https://kstar.kbs.co.kr/list_view.html?idx=314299","retrieved":1714697736924,"image":"https://entertainimg.kbsmedia.co.kr/cms/uploads/CONTENTS_20240503084110_bb69c0bbf90be8ce2f2fe6635374b484.jpg"},{"title":"'서울페스타2024' 김태욱  총감독 인터뷰 ...“Seoul is My Star” (KBS연예 ─ 연예)","contents":"<a href=\"https://kstar.kbs.co.kr/list_view.html?idx=314148\">\t<span class=\"img-box hh\">\n\t\t<span class=\"img-thum\">\n\t\t\t<span class=\"img-center\">\n\t\t\t\t<img src=\"https://entertainimg.kbsmedia.co.kr/cms/uploads/CONTENTS_20240502104256_0eace44d4ec1bce98fe3cd21672c3b85.JPG\" alt=\"대체 텍스트\">\n\t\t\t</span>\n\t\t</span>\n\t</span></a>\n\t<span class=\"txt\">\n\t\t<span class=\"max-progtit\"><a href=\"https://kstar.kbs.co.kr/list_view.html?idx=314148\">'서울페스타2024' 김태욱  총감독 인터뷰 ...“Seoul is My Star”</a></span>\n\t</span>","link":"https://kstar.kbs.co.kr/list_view.html?idx=314148","retrieved":1714614680990,"image":"https://entertainimg.kbsmedia.co.kr/cms/uploads/CONTENTS_20240502104256_0eace44d4ec1bce98fe3cd21672c3b85.JPG"},{"title":"[움짤] 윤아, '악마가 이사왔다' 프리티 크레이지 무드 (MBC 연예 ─ 아이돌)","contents":"<a href=\"/News/RetrieveNewsInfo/418191\">        <img src=\"//talkimg.imbc.com/TVianUpload/tvian/TViews/image/2024/05/18/6e48225f-f6c4-431a-9fbe-f6ed1d39312b.jpg\" alt=\"[움짤] 윤아, '악마가 이사왔다' 프리티 크레이지 무드\">        <div class=\"text-box\">            <p class=\"summary\">[움짤] 윤아, '악마가 이사왔다' 프리티 크레이지 무드</p>        </div>    </a>","link":"http://enews.imbc.com/News/RetrieveNewsInfo/418191","retrieved":1716037994610,"image":"http://talkimg.imbc.com/TVianUpload/tvian/TViews/image/2024/05/18/6e48225f-f6c4-431a-9fbe-f6ed1d39312b.jpg"},{"title":"[움짤] 태연, '집순이' 요정 출국 현장 (MBC 연예 ─ 아이돌)","contents":"<a href=\"/News/RetrieveNewsInfo/418190\">        <img src=\"//talkimg.imbc.com/TVianUpload/tvian/TViews/image/2024/05/18/767641f0-1f5d-4f21-a4d4-14960ac51778.jpg\" alt=\"[움짤] 태연, '집순이' 요정 출국 현장\">        <div class=\"text-box\">            <p class=\"summary\">[움짤] 태연, '집순이' 요정 출국 현장</p>        </div>    </a>","link":"http://enews.imbc.com/News/RetrieveNewsInfo/418190","retrieved":1716037994611,"image":"http://talkimg.imbc.com/TVianUpload/tvian/TViews/image/2024/05/18/767641f0-1f5d-4f21-a4d4-14960ac51778.jpg"},{"title":"‘쇼! 음악중심’ 다이몬, 풋풋한 비주얼+노련한 퍼포먼스 눈길 (MBC 연예 ─ 아이돌)","contents":"<a href=\"/News/RetrieveNewsInfo/418176\">        <img src=\"//talkimg.imbc.com/TVianUpload/tvian/TViews/image/2024/05/18/cf91544c-59cd-42d0-9a55-9b923c77416a.jpg\" alt=\"‘쇼! 음악중심’ 다이몬, 풋풋한 비주얼+노련한 퍼포먼스 눈길\">        <div class=\"text-box\">            <p class=\"summary\">‘쇼! 음악중심’ 다이몬, 풋풋한 비주얼+노련한 퍼포먼스 눈길</p>        </div>    </a>","link":"http://enews.imbc.com/News/RetrieveNewsInfo/418176","retrieved":1716023584719,"image":"http://talkimg.imbc.com/TVianUpload/tvian/TViews/image/2024/05/18/cf91544c-59cd-42d0-9a55-9b923c77416a.jpg"},{"title":"“사적으로 볼까?” 세븐틴 승관, 이이경 ‘돌아이’식 플러팅에 폭발 (놀뭐) (MBC 연예 ─ 아이돌)","contents":"<a href=\"/News/RetrieveNewsInfo/418170\">        <img src=\"//talkimg.imbc.com/TVianUpload/tvian/TViews/image/2024/05/18/4da54bc8-03d2-48ca-a66a-f4a1602f49dc.jpg\" alt=\"“사적으로 볼까?” 세븐틴 승관, 이이경 ‘돌아이’식 플러팅에 폭발 (놀뭐)\">        <div class=\"text-box\">            <p class=\"summary\">“사적으로 볼까?” 세븐틴 승관, 이이경 ‘돌아이’식 플러팅에 폭발 (놀뭐)</p>        </div>    </a>","link":"http://enews.imbc.com/News/RetrieveNewsInfo/418170","retrieved":1716016353575,"image":"http://talkimg.imbc.com/TVianUpload/tvian/TViews/image/2024/05/18/4da54bc8-03d2-48ca-a66a-f4a1602f49dc.jpg"},{"title":"에스파 카리나→윈터 숨멎 비주얼 과시…지젤, 럭키걸 등극할까 (놀토) (MBC 연예 ─ 아이돌)","contents":"<a href=\"/News/RetrieveNewsInfo/418168\">        <img src=\"//talkimg.imbc.com/TVianUpload/tvian/TViews/image/2024/05/18/3239ad8e-3650-4ddd-b074-e8df953b9b4f.jpg\" alt=\"에스파 카리나→윈터 숨멎 비주얼 과시…지젤, 럭키걸 등극할까 (놀토)\">        <div class=\"text-box\">            <p class=\"summary\">에스파 카리나→윈터 숨멎 비주얼 과시…지젤, 럭키걸 등극할까 (놀토)</p>        </div>    </a>","link":"http://enews.imbc.com/News/RetrieveNewsInfo/418168","retrieved":1716005761304,"image":"http://talkimg.imbc.com/TVianUpload/tvian/TViews/image/2024/05/18/3239ad8e-3650-4ddd-b074-e8df953b9b4f.jpg"},{"title":"[포토] \"완전 럭키비키잖아~!\" 아이브(IVE) 장원영 커피차 눈길 (MBC 연예 ─ 아이돌)","contents":"<a href=\"/News/RetrieveNewsInfo/418165\">        <img src=\"//talkimg.imbc.com/TVianUpload/tvian/TViews/image/2024/05/18/5cb7fba2-cfa0-4620-9233-d6847ebd7b1c.jpg\" alt=\"[포토] \" 완전=\"\" 럭키비키잖아~!\"=\"\" 아이브(ive)=\"\" 장원영=\"\" 커피차=\"\" 눈길\"=\"\">        <div class=\"text-box\">            <p class=\"summary\">[포토] \"완전 럭키비키잖아~!\" 아이브(IVE) 장원영 커피차 눈길</p>        </div>    </a>","link":"http://enews.imbc.com/News/RetrieveNewsInfo/418165","retrieved":1716002124133,"image":"http://talkimg.imbc.com/TVianUpload/tvian/TViews/image/2024/05/18/5cb7fba2-cfa0-4620-9233-d6847ebd7b1c.jpg"},{"title":"[포토] '쇼! 음악중심' NOWADAYS 미니팬미팅 성료 (MBC 연예 ─ 아이돌)","contents":"<a href=\"/News/RetrieveNewsInfo/418164\">        <img src=\"//talkimg.imbc.com/TVianUpload/tvian/TViews/image/2024/05/18/414635c3-a0a2-4a05-917f-cfbc2f854a76.jpg\" alt=\"[포토] '쇼! 음악중심' NOWADAYS 미니팬미팅 성료\">        <div class=\"text-box\">            <p class=\"summary\">[포토] '쇼! 음악중심' NOWADAYS 미니팬미팅 성료</p>        </div>    </a>","link":"http://enews.imbc.com/News/RetrieveNewsInfo/418164","retrieved":1716002124134,"image":"http://talkimg.imbc.com/TVianUpload/tvian/TViews/image/2024/05/18/414635c3-a0a2-4a05-917f-cfbc2f854a76.jpg"},{"title":"[포토] NOWADAYS 진혁, 하트 티켓 있어요? (MBC 연예 ─ 아이돌)","contents":"<a href=\"/News/RetrieveNewsInfo/418163\">        <img src=\"//talkimg.imbc.com/TVianUpload/tvian/TViews/image/2024/05/18/e6a3c923-ee5d-4f85-b5ea-dcae866da59a.JPG\" alt=\"[포토] NOWADAYS 진혁, 하트 티켓 있어요? \">        <div class=\"text-box\">            <p class=\"summary\">[포토] NOWADAYS 진혁, 하트 티켓 있어요? </p>        </div>    </a>","link":"http://enews.imbc.com/News/RetrieveNewsInfo/418163","retrieved":1716002124134,"image":"http://talkimg.imbc.com/TVianUpload/tvian/TViews/image/2024/05/18/e6a3c923-ee5d-4f85-b5ea-dcae866da59a.JPG"},{"title":"[포토] NOWADAYS 현빈, 나머지는 너의 몫 (MBC 연예 ─ 아이돌)","contents":"<a href=\"/News/RetrieveNewsInfo/418162\">        <img src=\"//talkimg.imbc.com/TVianUpload/tvian/TViews/image/2024/05/18/a74394c9-391e-4588-b2ed-6a40b1404143.JPG\" alt=\"[포토] NOWADAYS 현빈, 나머지는 너의 몫\">        <div class=\"text-box\">            <p class=\"summary\">[포토] NOWADAYS 현빈, 나머지는 너의 몫</p>        </div>    </a>","link":"http://enews.imbc.com/News/RetrieveNewsInfo/418162","retrieved":1716002124136,"image":"http://talkimg.imbc.com/TVianUpload/tvian/TViews/image/2024/05/18/a74394c9-391e-4588-b2ed-6a40b1404143.JPG"},{"title":"[포토] NOWADAYS 진혁, 포카 내꺼야 (MBC 연예 ─ 아이돌)","contents":"<a href=\"/News/RetrieveNewsInfo/418161\">        <img src=\"//talkimg.imbc.com/TVianUpload/tvian/TViews/image/2024/05/18/5e0cb176-9173-4b41-9901-dd55a94015a2.JPG\" alt=\"[포토] NOWADAYS 진혁, 포카 내꺼야\">        <div class=\"text-box\">            <p class=\"summary\">[포토] NOWADAYS 진혁, 포카 내꺼야</p>        </div>    </a>","link":"http://enews.imbc.com/News/RetrieveNewsInfo/418161","retrieved":1716002124138,"image":"http://talkimg.imbc.com/TVianUpload/tvian/TViews/image/2024/05/18/5e0cb176-9173-4b41-9901-dd55a94015a2.JPG"},{"title":"[포토] NOWADAYS 윤, 그대 바라보는 눈빛 (MBC 연예 ─ 아이돌)","contents":"<a href=\"/News/RetrieveNewsInfo/418160\">        <img src=\"//talkimg.imbc.com/TVianUpload/tvian/TViews/image/2024/05/18/67f13afd-8e04-4176-a2b0-cc378f7b9756.jpg\" alt=\"[포토] NOWADAYS 윤, 그대 바라보는 눈빛\">        <div class=\"text-box\">            <p class=\"summary\">[포토] NOWADAYS 윤, 그대 바라보는 눈빛</p>        </div>    </a>","link":"http://enews.imbc.com/News/RetrieveNewsInfo/418160","retrieved":1716002124139,"image":"http://talkimg.imbc.com/TVianUpload/tvian/TViews/image/2024/05/18/67f13afd-8e04-4176-a2b0-cc378f7b9756.jpg"},{"title":"김호중, 음주운전 시인… \"경찰 자진 출석할 것\" (다음 연예 ─ 뉴스 ─ 뮤직)","contents":"김호중(사진=이데일리DB)[이데일리 스타in 윤기백 기자] 교통사고를 내고 달아난 혐의를 받는 가수 김호중이 사고 열흘 만에 음주 운전을 시인했다. 김호중은 전국투어 창원 공연을 마친 뒤인 19일 오후 10시께 “나는 음주 운전을 했다”며 “크게 후회하고 반성하고 있다. 경찰 조사에 성실히 임하겠다”고 밝혔다. 이어 “저의 한순간의 잘못된 판단이 많은 분","link":"https://v.daum.net/v/20240520000655505","retrieved":1716131551826},{"title":"‘방VS민’ 싸움에 직접 나선 뉴진스, 괜찮을까? (다음 연예 ─ 뉴스 ─ 뮤직)","contents":"그룹 뉴진스가 하이브와 민희진 대표의 갈등에 탄원서로 공식적인 입장을 표명했다. 19일 가요계에 따르면 뉴진스 멤버의 부모들은 민 대표가 낸 의결권 행사 금지 가처분 신청 심문기일을 앞둔 지난 14일 엔터테인먼트 전문 변호사인 강진석 변호사를 선임해 법원에 탄원서를 제출했다. 이는 지난 17일 서울중앙지법에서 진행된 의결권 행사 금지 가처분 신청 심","link":"https://v.daum.net/v/20240520000208438","retrieved":1716131551827},{"title":"‘양심 뺑소니’ 김호중의 마이웨이 (다음 연예 ─ 뉴스 ─ 뮤직)","contents":"‘사고 내기 전 음주’ 국과수 판단에도 아랑곳 당당하게 콘서트 강행 “풀리지 않은 숙제 될 것 죄와 상처는 내가 받겠다” 걱정하는 팬심 교묘히 이용 가수 김호중이 뺑소니 사고에도 당당한 행보를 이어가고 있다. 김호중의 뺑소니 사고가 음주운전 의혹, 음주측정 회피 의혹, 사고 은폐 의혹, 증거인멸 의혹 등 온갖 논란이 더해지며 점입가경 사태로","link":"https://v.daum.net/v/20240520000105418","retrieved":1716131551828},{"title":"“그래도 믿었는데”…김호중 “아리스 자존심에 큰 상처, 조사 뒤 돌아오겠다” (다음 연예 ─ 뉴스 ─ 뮤직)","contents":"[스포츠서울 | 조은별기자] 음주운전을 시인한 가수 김호중이 팬클럽 아리스에 사죄의 뜻을 전했다. 김호중은 19일 오후 경남 창원 스포츠파크 실내체육관에서 ‘트바로티 클래식 아레나 투어’ 창원 공연을 마친 뒤 팬카페에 “진심으로 이번 일에 대해 우리 아리스(팬덤명) 식구들의 자존심에 큰 상처를 드려 죄송합니다”라고 고개를 숙였다. 그는 “술을 한잔이라","link":"https://v.daum.net/v/20240519231134151","retrieved":1716127902817},{"title":"김호중, 음주운전 인정→거짓 해명 들통 \"상처·실망감 드려\" (다음 연예 ─ 뉴스 ─ 뮤직)","contents":"[스타뉴스 | 윤성열 기자] 김호중 /사진제공=생각엔터테인먼트뺑소니 혐의로 경찰 조사를 받은 가수 김호중이 음주 운전을 한 사실을 시인했다. 관련 의혹을 부인한 지 사흘 만이다. 김호중은 19일 사과문을 통해 \"한순간의 잘못된 판단이 많은 분들에게 상처와 실망감을 드려 진심으로 죄송하다는 사과의 말을 전해드린다\"며 음주 운전을 인정했다. 김호중은 이","link":"https://v.daum.net/v/20240519230157090","retrieved":1716127902817},{"title":"버티던 김호중, 보도 4일만에 “음주운전했다, 후회하고 반성한다” (다음 연예 ─ 뉴스 ─ 뮤직)","contents":"[스포츠서울 | 조은별 기자] ‘뺑소니’ 사고 뒤 운전자 바꿔치기 의혹을 받고 있는 가수 김호중이 음주운전을 시인했다. 김호중은 19일 소속사 생각 엔터테인먼트를 통해 “저는 음주운전을 했다. 크게 후회하고 반성하고 있다. 경찰조사에 성실히 임하겠다”고 고개를 숙였다. 이어 “한순간의 잘못된 판단이 많은 분들에게 상처와 실망감을 드려 진심으로 죄송하다","link":"https://v.daum.net/v/20240519225743061","retrieved":1716127902817},{"title":"김호중 \"음주운전 했다\"…아니라던 소속사 \"되돌릴 수 없는 잘못 사과\" (다음 연예 ─ 뉴스 ─ 뮤직)","contents":"[스포츠한국 신영선 기자]&nbsp; 가수 김호중이 음주운전을 했다고 시인했다.&nbsp; 김호중은 19일 밤 소속사 생각엔터테인먼트를 통해 음주운전을 했다고 인정하는 사과문을 냈다.&nbsp; 그는 \"저의 한순간의 잘못된 판단이 많은 분들에게 상처와 실망감을 드려 진심으로 죄송하다는 사과의 말을 전해드리고 싶다\"며 \"저는 음주 운전을 했다\"고 밝혔다.&nbsp; 이어 \"크게","link":"https://v.daum.net/v/20240519225450025","retrieved":1716127902817},{"title":"'음주운전 인정' 김호중 측 \"경찰 출석일은 미정\" (다음 연예 ─ 뉴스 ─ 뮤직)","contents":"[티브이데일리 김지현 기자] 음주운전 사실을 인정한 가수 김호중이 경찰서에 자진 출석한다. 출석일은 미정이다. 19일 소속사 생각엔터테인먼트는 “자사 아티스트 김호중 논란과 더불어 당사의 잘못된 판단으로 사회적 물의를 일으킨 점 고개 숙여 사과드”며 “최초 공식 입장서부터 지금까지 상황을 숨기기에 급급했다. 진실되게 행동하지 못한 점 또한 진심으로 사과드린","link":"https://v.daum.net/v/20240519224311917","retrieved":1716127902818},{"title":"\"어리석은 내 모습 너무 싫어\"… 김호중 음주운전 심경 (다음 연예 ─ 뉴스 ─ 뮤직)","contents":"김호중(사진=뉴스1)[이데일리 스타in 윤기백 기자] “진심으로 이번 일에 대해 우리 아리스(팬덤명) 식구들의 자존심에 큰 상처를 드려 죄송합니다.” 음주 운전을 뒤늦게 시인한 가수 김호중이 팬들에게 사과의 말을 전했다. 김호중은 19일 공식 팬카페를 통해 “술을 한 잔이라도 입에 대면 핸들을 잡으면 안 된다라는 것을 너무나도 잘 알고 있다”며 “저의 어","link":"https://v.daum.net/v/20240519223545888","retrieved":1716127902820},{"title":"김호중, 음주운전 인정 \"크게 후회하고 반성하고 있다\" (다음 연예 ─ 뉴스 ─ 뮤직)","contents":"[티브이데일리 김지하 기자] 뺑소니 혐의에 음주운전 의혹을 받았던 가수 김호중(33)이 음주운전을 인정했다. 소속사 생각엔터테인먼트는 19일 저녁 공식입장을 내고 \"김호중 논란과 더불어 당사의 잘못된 판단으로 사회적 물의를 일으킨 점 고개 숙여 사과드린다\"라고 밝혔다. \"김호중은 음주운전을 하지 않았다\"는 등 사건이 알려진 직후부터 내온 공식입장들과 관","link":"https://v.daum.net/v/20240519222607825","retrieved":1716127902821},{"title":"김호중, 결국 음주운전 시인… \"크게 후회하고 반성\" (다음 연예 ─ 뉴스 ─ 뮤직)","contents":"김호중[이데일리 스타in 윤기백 기자] “저는 음주 운전을 했습니다. 크게 후회하고 반성하고 있습니다.” 교통사고를 내고 달아난 혐의를 받는 가수 김호중이 음주 운전을 뒤늦게 인정했다. 소속사 생각엔터테인먼트는 19일 “자사 아티스트 김호중 논란과 더불어 당사의 잘못된 판단으로 사회적 물의를 일으킨 점 고개 숙여 사과드린다”며 “최초 공식 입장에서부터 지","link":"https://v.daum.net/v/20240519221212711","retrieved":1716124495418},{"title":"\"크게 후회하고 반성\" 김호중, 결국 음주운전 혐의 시인 (다음 연예 ─ 뉴스 ─ 뮤직)","contents":"[스타뉴스 | 윤성열 기자] 김호중 /사진=뉴스1 /사진=(서울=뉴스1) 권현진 기자뻉소니 혐의로 입건된 가수 김호중이 결국 음주운전을 시인했다. 소속사 생각엔터테인먼트 측은 19일 \"김호중 논란과 더불어 당사의 잘못된 판단으로 사회적 물의를 일으킨 점 고개 숙여 사과드린다\"며 \"최초 공식 입장에서부터 지금까지 상황을 숨기기에 급급했다. 진실되게 행동하","link":"https://v.daum.net/v/20240519220941680","retrieved":1716124495419},{"title":"'자진 출석 발표' 김호중,  \"죄송하다, 모든 진실 밝혀질 것\" (다음 연예 ─ 뉴스 ─ 뮤직)","contents":"[티브이데일리 김지현 기자] 음주운전 논란에 휩싸인 가수 김호중이 19일 열린 콘서트에서 사과의 말을 전했다. 김호중은 이날 오후 창원스포츠파크실내체육관에서 열린 콘서트에서 \"“죄송하다. 죄는 제가 지었지, 여러분들은 공연을 보러 오신 것 뿐\"이라고 사과하며 고개를 숙였다. 김호중은 전날 열린 공연에서도 “모든 진실은 밝혀질 것”이라며 “모든 죄와 상처는","link":"https://v.daum.net/v/20240519214607513","retrieved":1716124495419},{"title":"민희진 기자회견 후 첫 입장, 하이브 \"증거 충분\" 반박...31일 해임안 코앞 (다음 연예 ─ 뉴스 ─ 뮤직)","contents":"[OSEN=연휘선 기자] 하이브로부터 걸그룹 뉴진스 소속사 어도어의 경영권 탈취 의혹을 받는 민희진 대표가 기자회견 후 처음으로 심경을 밝혔다.&nbsp; 민희진 대표는 19일 장문의 글을 내고 다시 한번 입장을 밝혔다. \"기자회견 이후 처음으로 개인의 입장에서 글을 쓴다\"고 운을 뗀 그는 \"딱딱한 입장문의 형식을 빌지 않고 이런 글을 쓰는 이유는 밝히고자 하는","link":"https://v.daum.net/v/20240519214545509","retrieved":1716124495421},{"title":"하이브 측 “민희진, 뉴진스와 관계만 부각? 안타까워” (다음 연예 ─ 뉴스 ─ 뮤직)","contents":"연예기획사 하이브가 법적 분쟁을 이어가고 있는 레이블 어도어 민희진 대표의 입장문에 선을 그었다. 하이브 측은 19일 “중요한 법리적 판단을 앞둔 시점에 개인의 감정을 앞세운 입장문을 배포한 민희진 대표의 행태에 안타까움을 표한다”며 “아티스트(뉴진스)가 언급되지 않길 바란다면서, 아티스트와 본인 관계를 부각시키며 끌어들인 행태 또한 매우 부적절하다”","link":"https://v.daum.net/v/20240519213922457","retrieved":1716124495421},{"title":"슬리피도 허경환도 \"저 아니에요\".. 김호중 술자리 동석 루머 부인 (다음 연예 ─ 뉴스 ─ 스타)","contents":"[TV리포트=이혜미 기자] 개그맨 허경환에 이어 래퍼 슬리피가 '음주 뺑소니' 혐의를 받는 김호중과 술자리를 함께했다는 루머에 대해 부인했다. 19일 슬리피의 소셜 계정엔 \"나 아니다. 다들 신경 써주셔서 감사하다\"라는 내용의 글이 게시됐다. 슬리피는 또 딸을 품에 안은 사진과 함께 \"5월은 가정의 달\"이라고 덧붙이는 것으로 루머를 일축했다. 이는 앞서 허","link":"https://v.daum.net/v/20240520000500478","retrieved":1716131555736},{"title":"'살아있길 잘했어'...서정희의 '희로애락' (다음 연예 ─ 뉴스 ─ 스타)","contents":"\"절대 다시 일어설 수 없다는 사람들에게\" 던지는 메시지 일상과 삶을 되돌아 본 에세이집 '살아있길 잘했어' 출간 [더팩트ㅣ강일홍 기자] 인생은 희로애락, 기쁨과 즐거움만 있는 게 아니라 걱정과 슬픔이 늘 공존합니다. 생각하기에 따라 차이는 있겠지만 그 속에 행복도 있고 불행도 있습니다. 그런데 유독 풍파를 많이 겪는 사람들도 있습니다. 영화 속의 주","link":"https://v.daum.net/v/20240520000121424","retrieved":1716131555736},{"title":"4%대 시청률에도 '대박' 터진 이유 (다음 연예 ─ 뉴스 ─ 스타)","contents":"2049 타깃 시청률에 초점…높은 화제성까지 '기대 이상 성과' '선친자' '월요병 타파' 등 여러 수식어가 탄생할 정도로 tvN '선재 업고 튀어'가 열풍을 넘어 신드롬을 일으키고 있다. 작품을 향한 열기는 곳곳에서 확인할 수 있었고 시청자들의 과몰입은 현실로도 이어졌다. 일례로 류선재가 속한 그룹 이클립스의 방송 출연 요청이 쇄도했으며 작품 속 주","link":"https://v.daum.net/v/20240520000049412","retrieved":1716131555736},{"title":"드라마에 이어 新예능도…웃을 일 없는 KBS (다음 연예 ─ 뉴스 ─ 스타)","contents":"4월 25일 '라인업 설명회' 개최…\"젊은 세대를 주 시청층으로\" '더 시즌즈'부터 '싱크로유'까지 화제성 낮아 [더팩트ㅣ문화영 기자] 최근 KBS 드라마가 시청률 부진을 면치 못하고 있는 가운데 예능 역시 저조한 성적을 받고 있다. AI를 도입하고 국민 MC 유재석을 데려오는 등 시청자를 사로잡기 위한 노력이 진행 중이지만 별다른 효과를 보지 못해","link":"https://v.daum.net/v/20240520000036408","retrieved":1716131555736},{"title":"기안84 \"'연예대상' 받고 출연료 200만원 올라\" (다음 연예 ─ 뉴스 ─ 스타)","contents":"[서울=뉴시스]이재훈 기자 = 웹툰 작가 겸 방송인 기안84가 지난해 'MBC 연예대상'에서 대상을 받고 달라진 위상을 전했다. 기안84는 19일 방송된 KBS 2TV 예능물 '사장님 귀는 당나귀 귀'(이하 '사당귀')에서 정준하가 전화통화 중 \"대상 받고 출연료 많이 올랐냐\"라고 묻자 \"한 200만원 정도 올려줬다\"고 답했다. 이를 보던 '사당귀' M","link":"https://v.daum.net/v/20240520000017399","retrieved":1716131555737},{"title":"'음주운전' 김호중, 팬카페에 심경글 \"죄지은 사람, 내 모습 싫어\" (다음 연예 ─ 뉴스 ─ 스타)","contents":"[스타뉴스 | 이예지 기자] 가수 김호중이 21일 오후 서울 영등포구 여의도동 KBS홀에서 진행된 '2023 서울 드라마 어워즈' 레드카펫 행사에 참석하고 있다. 2023.09.21 /사진=김창현가수 김호중이 음주운전을 시인하고 팬들에게 심경을 전했다. 김호중은 19일 공식 팬카페에 '죄송합니다'라는 제목의 글을 통해 \"술을 한잔이라도 입에 대면 핸들을","link":"https://v.daum.net/v/20240519235545364","retrieved":1716131555737},{"title":"'히어로는 아닙니다만' 장기용, 천우희에 청혼 \"결혼이든 사랑이든 할 일 할 것\" (다음 연예 ─ 뉴스 ─ 스타)","contents":"[스포츠투데이 백지연 기자] '히어로는 아닙니다만' 장기용이 천우희에게 프러포즈를 했다. 19일 밤 방송된 JTBC 주말드라마 '히어로는 아닙니다만'에서 복귀주(장기용)가 도다해(천우희)와 결혼을 결심했다. 이날 방송에서 복귀주는 복만흠(고두심)의 만류에도 도다해와의 결혼을 결심했다. 도다해는 복귀주에 \"정말 여사님이 결혼하는 꿈이 꿨다고 했냐\"고 물었","link":"https://v.daum.net/v/20240519234818332","retrieved":1716131555739},{"title":"\"진실 밝혀진다\"더니…김호중, 음주운전 인정 \"후회·반성한다\" (다음 연예 ─ 뉴스 ─ 스타)","contents":"[스포티비뉴스=장진리 기자] 트로트 가수 김호중(33)이 음주운전 사실을 인정했다. 김호중은 19일 소속사 생각엔터테인먼트를 통해 음주운전 사실을 시인하고 경찰의 조사를 성실히 받겠다고 밝혔다. 김호중은 지난 9일 밤 11시 40분께 서울 강남구 압구정동 한 도로에서 마주오던 택시와 접촉 사고를 낸 뒤 도주한 혐의를 받고 있다. 사고 피해자인 택시","link":"https://v.daum.net/v/20240519234543325","retrieved":1716131555741},{"title":"‘전교 1등만 찾아왔다’... 정려원X위하준, 일타강사 되나 ‘기대감 만발’ (다음 연예 ─ 뉴스 ─ 스타)","contents":"정려원과 위하준의 무료 강의에 단 한명의 학생이 찾아왔다. 19일 오후 방송된 tvN 토일드라마 ‘졸업’(극본 박경화, 연출 안판석)에서 서혜진(정려원 분)과 이준호(위하준 분)은 사제특강 무료 강의를 준비했다. 강의 당일 혜진은 “갑자기 당황하고 목소리 갈라질 때 있을 거야. 그럴 땐 나 봐, 아는 사람 얼굴 보면 좀 괜찮아져”라고 이준호에게 당부했다.","link":"https://v.daum.net/v/20240519234501323","retrieved":1716131555742},{"title":"\"김호중 또 술마셨나\" 자존심 운운…'음주 인정' 심경글 빈축 (다음 연예 ─ 뉴스 ─ 스타)","contents":"(엑스포츠뉴스 김예나 기자) 가수 김호중이 음주운전을 인정하기 전 팬카페에 남긴 글이 화제를 모으고 있다.&nbsp; 19일 김호중이 뺑소니 사고 열흘 만에 음주운전 사실을 인정, 경찰 조사에 임하겠다는 입장을 밝혔다.&nbsp; 그는 소속사 생각엔터테인먼트를 통해 \"제 한 순간 잘못된 판단이 많은 분들에게 상처와 실망감을 드려 진심으로 죄송하다는 사과의 말을 전하고 싶다.","link":"https://v.daum.net/v/20240519234140319","retrieved":1716131555743},{"title":"‘뺑소니’ 김호중, 음주운전 결국 시인 “잘못된 판단” (다음 연예 ─ 뉴스 ─ 스타)","contents":"뺑소니 사고를 낸 가수 김호중이 사고 열흘 만에 음주운전 사실을 인정했다. 19일 김호중은 창원 콘서트를 마친 뒤 소속사 생각엔터테인먼트를 통해 “음주운전을 했다”며 “크게 후회하고 반성 중이며 경찰 조사에 성실히 임하겠다”고 밝혔다. 이어 “한순간 잘못된 판단이 많은 분에게 실망감을 드려 진심으로 죄송하다”고 했다. 소속사 생각엔터테인먼트 역시 사과했","link":"https://v.daum.net/v/20240519233901306","retrieved":1716131555745},{"title":"'히어로는 아닙니다만' 장기용, 고두심 반대에도 천우희와 결혼 결심 {TV캡처] (다음 연예 ─ 뉴스 ─ 스타)","contents":"[스포츠투데이 백지연 기자] '히어로는 아닙니다만' 고두심이 장기용의 결혼을 반대했지만 고집을 꺾지 못했다. 19일 밤 방송된 JTBC 주말드라마 '히어로는 아닙니다만'에서 복귀주(장기용)가 도다해(천우희)와 결혼을 결심했다. 이날 방송에서 복만흠(고두심)은 꿈을 꾼 뒤 다도해네 찜질방에 다녀온 복귀주에게 \"다시는 거기 발 들이지 말아라. 또렷하게 봤다","link":"https://v.daum.net/v/20240519233122282","retrieved":1716131555746},{"title":"콘서트 끝나니 이제야…김호중, 열흘만 음주운전 인정 \"크게 후회하고 반성\" (다음 연예 ─ 뉴스 ─ 스타)","contents":"[스포츠조선닷컴 이우주 기자] 음주운전을 완강히 부인하던 가수 김호중이 사고 열흘 후에야 음주운전을 인정했다. 김호중 소속사 생각엔터테인먼트 측은 19일 \"자사 아티스트 김호중 논란과 더불어 당사의 잘못된 판단으로 사회적 물의를 일으킨 점 고개 숙여 사과 드린다. 최초 공식 입장에서부터 지금까지 상황을 숨기기에 급급했다. 진실되게 행동하지","link":"https://v.daum.net/v/20240519232853270","retrieved":1716131555747},{"title":"'음주운전 시인' 김호중, \"죄지은 사람이 말 길면 뭐하나..결과 나오면 돌아올것\" (다음 연예 ─ 뉴스 ─ 스타)","contents":"[OSEN=하수정 기자] 가수 김호중이 음주 뺑소니 혐의를 받는 가운데, 팬들에게 심경을 고백했다. 김호중은 19일 오후 자신의 팬카페를 통해 음주운전을 고백하며 심경을 드러냈다. 그는 \"진심으로 이번일에 대해 우리 아리스(팬덤) 식구들의 자존심에 큰 상처를 드려 죄송합니다\"라며 \"술을 한잔이라도 입에 대면 핸들을 잡으면 안된다는 것을 너무나도 잘 알고","link":"https://v.daum.net/v/20240519232447242","retrieved":1716131555749},{"title":"'음주운전' 김호중 \"죄 지은 사람, 말이 길면 뭐하겠습니까\" (다음 연예 ─ 뉴스 ─ 스타)","contents":"[서울=뉴시스]이재훈 기자 = 트로트가수 김호중이 음주운전을 시인하고 사과한 데 이어 팬클럽에게도 고개를 숙였다. 김호중은 19일 오후 자신의 팬클럽에 \"진심으로 이번일에 대해 우리 아리스 식구들의 자존심에 큰 상처를 드려 죄송하다\"며 사과했다. \"술을 한잔이라도 입에 대면 '핸들을 잡으면 안 된다'라는 것을 너무나도 잘 알고 있다\"면서 \"저의 어리석","link":"https://v.daum.net/v/20240519232434240","retrieved":1716131555750},{"title":"“이혼 임박” 제니퍼 로페즈, 벤 애플렉과 결별 수순 “전문 변호사 고용” (다음 연예 ─ 뉴스 ─ 해외)","contents":"[마이데일리 = 곽명동 기자]세계적 가수 제니퍼 로페즈(54)와 ‘배트맨’ 벤 애플렉(51)의 이혼이 임박했다. 한 소식통은 18일(현지시간) ‘인 터치’에 \"로페즈는 애플렉과 이혼하기 위해 “위기를 관리하는 홍보 전문가를 고용했다”고 보도했다. 이어 “로라 바서가 두 사람의 이혼을 처리할 것으로 보인다”면서 “바서는 애플렉과 제니퍼 가너의 이혼을 중재","link":"https://v.daum.net/v/20240519214624517","retrieved":1716124504021},{"title":"벤 애플렉, 결혼 반지 뺐다..'20년만 재결합' 제니퍼 로페즈와 이혼? (다음 연예 ─ 뉴스 ─ 해외)","contents":"[OSEN=선미경 기자] 배우 벤 애플렉과 제니퍼 로페즈 부부의 이혼이 공식화 됐다. 이혼 위기 속 벤 애플렉이 결혼반지를 빼고 외출한 모습이 포착된 것. 18일 페이지 식스는 벤 애플렉이 아내 제니퍼 로페즈와 이혼 루머 속 처음으로 결혼 반지 없이 외출에 나섰다고 보도했다. 보도에 따르면 이들은 지난 토요일 자녀의 연주회에 참석하기 위해 외출했다. 벤","link":"https://v.daum.net/v/20240519162030852","retrieved":1716106643422},{"title":"'걸그룹' 센터 멤버, 남자 배우 여러명과 '바람'...충격 폭로 나왔다 (다음 연예 ─ 뉴스 ─ 해외)","contents":"[TV리포트=유소연 기자] 일본 방송인 겸 정치인 히가시 고쿠마루 히데오가 한 아이돌 그룹과 관련된 깜짝 폭로를 해 눈길을 끈다. 16일(현지 시간) 배우 겸 개그맨 미야사코 히로유키(54)가 자신의 유튜브 채널에 \"연예계 BIG3와 프리 토크를 했더니 큰일 났습니다\"라는 제목의 영상을 올렸다. 영상에는 개그맨 타시로 마사시(67)와 정치인 겸 정치인 히가","link":"https://v.daum.net/v/20240519152033492","retrieved":1716102903140},{"title":"“결혼반지 뺐다” 벤 애플렉, 제니퍼 로페즈와 이혼 공식화? (다음 연예 ─ 뉴스 ─ 해외)","contents":"[마이데일리 = 곽명동 기자]벤 애플렉(51)이 결혼 반지를 뺐다. 제니퍼 로페즈(54)와 이혼이 공식화되는 분위기라는 주장이 나오고 있다. 페이지식스는 18일(현지시간) “벤 애플렉이 운전 중 왼손을 들어올리는 모습이 포착됐다”면서 “그는 결혼 반지를 끼지 않았다”고 전했다. 이어 “결혼 반지가 없는 모습이 목격되면서 그와 로페즈가 이혼으로 향하고 있","link":"https://v.daum.net/v/20240519111141201","retrieved":1716086214620},{"title":"'브리저튼3' 니콜라 코클란 \"출연료 17만 원 받던 나...30대 되고 터졌다\" (다음 연예 ─ 뉴스 ─ 해외)","contents":"[TV리포트=한아름 기자] 넷플릭스 시리즈 '브리저튼'으로 전 세계의 주목을 받은 배우 니콜라 코클란(37)이 과거 경제적인 어려움을 겪었다고 고백해 눈길이 쏠렸다. 16일(현지 시간), 잡지 '마리끌레르'가 배우 니콜라 코클란과 진행한 인터뷰 전문을 공개했다. 인터뷰에서 니콜란 코클란은 무명 시절을 회상하며 주인공이 된 현재 자신의 모습에 자랑스러워했다.","link":"https://v.daum.net/v/20240519100141026","retrieved":1716080508164},{"title":"힙합거물 콤스 8년전 여자친구 캐시 폭행 영상 공개돼 파문 (다음 연예 ─ 뉴스 ─ 해외)","contents":"(로스앤젤레스=연합뉴스) 임미나 특파원 = '퍼프대디'라는 예명으로 유명한 미국 힙합계의 거물 션 디디 콤스(54)가 8년 전에 여자친구인 가수 캐시(본명 카산드라 벤투라)를 심하게 폭행하는 장면이 담긴 동영상이 공개돼 파문이 일고 있다. 미 CNN 방송은 지난 17일(현지시간) 2016년 3월 5일 로스앤젤레스(LA)의 한 호텔 복도에서 촬영된 CCTV","link":"https://v.daum.net/v/20240519042348193","retrieved":1716063273621},{"title":"김호중, 음주운전 시인… \"경찰 자진 출석할 것\" [종합] (네이버 TV연예 ─ 최신뉴스 ─ 뮤직)","contents":"김호중(사진=이데일리DB) 교통사고를 내고 달아난 혐의를 받는 가수 김호중이 사고 열흘 만에 음주 운전을 시인했다. 김호중은 전국투어 창원 공연을 마친 뒤인 19일 오후 10시께 “나는 음주 운전을 했다”며 “크게","link":"https://m.entertain.naver.com/now/article/018/0005743528","retrieved":1716131565703},{"title":"‘방VS민’ 싸움에 직접 나선 뉴진스, 괜찮을까?[스경X초점] (네이버 TV연예 ─ 최신뉴스 ─ 뮤직)","contents":"그룹 뉴진스가 하이브와 민희진 대표의 갈등에 탄원서로 공식적인 입장을 표명했다. 19일 가요계에 따르면 뉴진스 멤버의 부모들은 민 대표가 낸 의결권 행사 금지 가처분 신청 심문기일을 앞둔 지난 14일 엔터테인먼트 전","link":"https://m.entertain.naver.com/now/article/144/0000962646","retrieved":1716131565704},{"title":"‘양심 뺑소니’ 김호중의 마이웨이 (네이버 TV연예 ─ 최신뉴스 ─ 뮤직)","contents":"‘사고 내기 전 음주’ 국과수 판단에도 아랑곳 당당하게 콘서트 강행 “풀리지 않은 숙제 될 것 죄와 상처는 내가 받겠다” 걱정하는 팬심 교묘히 이용 가수 김호중이 뺑소니 사고에도 당당한 행보를 이어가고 있다. 김호중","link":"https://m.entertain.naver.com/now/article/144/0000962644","retrieved":1716131565706},{"title":"[입장전문] 김호중, 결국 음주운전 시인 \"저는 음주 운전을 하였습니다\" (네이버 TV연예 ─ 최신뉴스 ─ 뮤직)","contents":"가수 김호중이 음주운전 사고를 인정했다. 김호중의 소속사 생각엔터테인먼트는 19일 입장문을 배포하고 \"김호중은 경찰에 자진 출석하여 음주운전 등 사실관계를 인정하며 경찰 조사에 성실히 임하겠다\"라고 밝혔다. 더불어","link":"https://m.entertain.naver.com/now/article/030/0003207143","retrieved":1716131565709},{"title":"김호중, 사고 열흘 만에 \"음주운전 했다…크게 후회·반성\"(종합2보) (네이버 TV연예 ─ 최신뉴스 ─ 뮤직)","contents":"\"상처와 실망 드려 죄송…경찰 조사에 성실히 임하겠다\" 소속사도 \"상황 숨기기 급급…진실되게 행동하지 못한 점 사과\" 줄곧 음주 사실 부인해왔으나 정황 증거 속속 드러나며 음주 시인 (서울=연합뉴스) 최주성 이미령","link":"https://m.entertain.naver.com/now/article/001/0014695473","retrieved":1716131565711},{"title":"'음주운전' 김호중 \"죄 지은 사람, 말이 길면 뭐하겠습니까\" (네이버 TV연예 ─ 최신뉴스 ─ 뮤직)","contents":"트로트가수 김호중이 음주운전을 시인하고 사과한 데 이어 팬클럽에게도 고개를 숙였다. 김호중은 19일 오후 자신의 팬클럽에 \"진심으로 이번일에 대해 우리 아리스 식구들의 자존심에 큰 상처를 드려 죄송하다\"며 사과했다.","link":"https://m.entertain.naver.com/now/article/003/0012554231","retrieved":1716131565712},{"title":"“그래도 믿었는데”…김호중 “아리스 자존심에 큰 상처, 조사 뒤 돌아오겠다” [전문] (네이버 TV연예 ─ 최신뉴스 ─ 뮤직)","contents":"김호중. 사진 | 두미 음주운전을 시인한 가수 김호중이 팬클럽 아리스에 사죄의 뜻을 전했다. 김호중은 19일 오후 경남 창원 스포츠파크 실내체육관에서 ‘트바로티 클래식 아레나 투어’ 창원 공연을 마친 뒤 팬카페에 “","link":"https://m.entertain.naver.com/now/article/468/0001061532","retrieved":1716131565714},{"title":"김호중, 음주운전 인정→거짓 해명 들통 \"상처·실망감 드려\" [종합] (네이버 TV연예 ─ 최신뉴스 ─ 뮤직)","contents":"뺑소니 혐의로 경찰 조사를 받은 가수 김호중이 음주 운전을 한 사실을 시인했다. 관련 의혹을 부인한 지 사흘 만이다. 김호중은 19일 사과문을 통해 \"한순간의 잘못된 판단이 많은 분들에게 상처와 실망감을 드려 진심으","link":"https://m.entertain.naver.com/now/article/108/0003236561","retrieved":1716127917411},{"title":"경찰, '음주운전 시인' 김호중과 출석조사 일정 조율 중 (네이버 TV연예 ─ 최신뉴스 ─ 뮤직)","contents":"조성하 이재훈 기자 = 경찰이 뺑소니 혐의에 음주운전 의혹도 더해진 트로트 가수 김호중(33)과 출석 조사 일정을 조율 중이다. 김호중이 19일 음주운전을 시인함에 따라 경찰 수사는 속도가 더해질 전망이다. 서울 강","link":"https://m.entertain.naver.com/now/article/003/0012554227","retrieved":1716127917412},{"title":"버티던 김호중, 보도 4일만에 “음주운전했다, 후회하고 반성한다” [전문] (네이버 TV연예 ─ 최신뉴스 ─ 뮤직)","contents":"김호중. 사진 | 스포츠서울DB ‘뺑소니’ 사고 뒤 운전자 바꿔치기 의혹을 받고 있는 가수 김호중이 음주운전을 시인했다. 김호중은 19일 소속사 생각 엔터테인먼트를 통해 “저는 음주운전을 했다. 크게 후회하고 반성하","link":"https://m.entertain.naver.com/now/article/468/0001061530","retrieved":1716127917414},{"title":"김호중, 사고 열흘 만에 음주운전 결국 시인…\"크게 후회\"(종합) (네이버 TV연예 ─ 최신뉴스 ─ 뮤직)","contents":"\"상처와 실망 드려 죄송…경찰 조사에 성실히 임하겠다\" 소속사도 \"상황 숨기기 급급…진실되게 행동하지 못한 점 사과\" 음주 운전과 뺑소니 의혹을 받는 가수 김호중(33)이 사고 열흘 만에 음주운전 사실을 시인했다.","link":"https://m.entertain.naver.com/now/article/001/0014695467","retrieved":1716127917415},{"title":"\"어리석은 내 모습 너무 싫어\"… 김호중 음주운전 심경 [전문] (네이버 TV연예 ─ 최신뉴스 ─ 뮤직)","contents":"김호중(사진=뉴스1) “진심으로 이번 일에 대해 우리 아리스(팬덤명) 식구들의 자존심에 큰 상처를 드려 죄송합니다.” 음주 운전을 뒤늦게 시인한 가수 김호중이 팬들에게 사과의 말을 전했다. 김호중은 19일 공식 팬카","link":"https://m.entertain.naver.com/now/article/018/0005743513","retrieved":1716127917418},{"title":"\"저는 음주운전을 했습니다\" 김호중 결국 인정…\"크게 후회하고 반성\"[전문] (네이버 TV연예 ─ 최신뉴스 ─ 뮤직)","contents":"“저는 음주운전을 하였습니다.” 가수 김호중이 음주운전 사실을 인정하고 사과했다. 김호중은 19일 오후 10시 넘어 소속사 생각엔터테인먼트를 통해 음주운전 시인을 포함한 사과문을 냈다. 김호중은 “저의 한순간의 잘못","link":"https://m.entertain.naver.com/now/article/241/0003351276","retrieved":1716127917418},{"title":"김호중, 결국 음주운전 인정 \"크게 후회하고 반성..경찰 조사 성실히 임할 것\"[전문] (네이버 TV연예 ─ 최신뉴스 ─ 뮤직)","contents":"김호중이 결국 음주운전을 인정했다. 19일 김호중의 소속사 생각엔터테인먼트 측은 공식 보도자료를 통해 \"자사 아티스트 김호중 논란과 더불어 당사의 잘못된 판단으로 사회적 물의를 일으킨 점 고개 숙여 사과드린다. 최초","link":"https://m.entertain.naver.com/now/article/112/0003698174","retrieved":1716127917419},{"title":"김호중, 결국 음주운전 시인…\"경찰조사 임하겠다\"(종합) (네이버 TV연예 ─ 최신뉴스 ─ 뮤직)","contents":"뺑소니 혐의에 음주운전 의혹도 더해진 트로트 가수 김호중(33)이 결국 음주운전을 시인했다. 김호중은 19일 소속사 생각엔터테인먼트를 통해 \"저는 음주 운전을 했다. 크게 후회하고 반성하고 있다. 경찰 조사에 성실히","link":"https://m.entertain.naver.com/now/article/003/0012554222","retrieved":1716127917422},{"title":"김호중, 음주운전 시인…\"경찰 조사 성실히 임할 것\" (네이버 TV연예 ─ 최신뉴스 ─ 뮤직)","contents":"음주 운전과 뺑소니 의혹을 받는 가수 김호중(33)이 음주운전 사실을 시인했다. 김호중은 19일 소속사 생각엔터테인먼트를 통해 밝힌 사과문에서 \"저는 음주운전을 하였다\"며 \"크게 후회하고 반성하고 있다. 경찰 조사에","link":"https://m.entertain.naver.com/now/article/001/0014695464","retrieved":1716127917423},{"title":"김호중, 결국 음주운전 시인… \"크게 후회하고 반성\" [공식] (네이버 TV연예 ─ 최신뉴스 ─ 뮤직)","contents":"김호중 “저는 음주 운전을 했습니다. 크게 후회하고 반성하고 있습니다.” 교통사고를 내고 달아난 혐의를 받는 가수 김호중이 음주 운전을 뒤늦게 인정했다. 소속사 생각엔터테인먼트는 19일 “자사 아티스트 김호중 논란과","link":"https://m.entertain.naver.com/now/article/018/0005743509","retrieved":1716124510376},{"title":"김호중 \"음주운전 했다…크게 후회·반성\"(1보) (네이버 TV연예 ─ 최신뉴스 ─ 뮤직)","contents":"뺑소니 혐의에 음주운전 의혹도 더해진 트로트 가수 김호중(33)이 결국 음주운전 혐의를 인정했다. 김호중은 19일 소속사 생각엔터테인먼트를 통해 \"저는 음주 운전을 했다. 크게 후회하고 반성하고 있다. 경찰 조사에","link":"https://m.entertain.naver.com/now/article/003/0012554218","retrieved":1716124510376},{"title":"\"크게 후회하고 반성\" 김호중, 결국 음주운전 혐의 시인 [속보] (네이버 TV연예 ─ 최신뉴스 ─ 뮤직)","contents":"뻉소니 혐의로 입건된 가수 김호중이 결국 음주운전을 시인했다. 소속사 생각엔터테인먼트 측은 19일 \"김호중 논란과 더불어 당사의 잘못된 판단으로 사회적 물의를 일으킨 점 고개 숙여 사과드린다\"며 \"최초","link":"https://m.entertain.naver.com/now/article/108/0003236557","retrieved":1716124510379},{"title":"김호중, 경찰 자진 출석할 듯…\"조사받고 입장낸다\" (네이버 TV연예 ─ 최신뉴스 ─ 뮤직)","contents":"뺑소니 혐의에 음주운전 의혹도 더해진 트로트 가수 김호중(33)이 경찰에 자진 출석할 것으로 보인다. 19일 김호중 소속사 생각엔터테인먼트 등에 따르면, 김호중은 곧 경찰에 스스로 출석한다. 경찰 조사를 마친 뒤 공","link":"https://m.entertain.naver.com/now/article/003/0012554216","retrieved":1716124510379},{"title":"하이브 측 “민희진, 뉴진스와 관계만 부각? 안타까워”[공식] (네이버 TV연예 ─ 최신뉴스 ─ 뮤직)","contents":"연예기획사 하이브가 법적 분쟁을 이어가고 있는 레이블 어도어 민희진 대표의 입장문에 선을 그었다. 하이브 측은 19일 “중요한 법리적 판단을 앞둔 시점에 개인의 감정을 앞세운 입장문을 배포한 민희진 대표의 행태에 안","link":"https://m.entertain.naver.com/now/article/144/0000962632","retrieved":1716124510379},{"title":"김호중 측 \"경찰 자진출석해 조사받고 입장 낼것…날짜 협의중\" (네이버 TV연예 ─ 최신뉴스 ─ 뮤직)","contents":"음주 운전과 뺑소니 의혹을 받는 가수 김호중(33)이 경찰에 자진 출석하겠다는 입장을 밝혔다. 김호중 소속사 생각엔터테인먼트 관계자는 19일 연합뉴스와 통화에서 \"김호중은 경찰에 자진 출석해 성실히 조사에 임할 것\"","link":"https://m.entertain.naver.com/now/article/001/0014695449","retrieved":1716124510381},{"title":"김호중 김천공연 취소 기로…창원 공연서 \"죄는 제가 지어\"(종합) (네이버 TV연예 ─ 최신뉴스 ─ 뮤직)","contents":"전국투어 공동주최 SBS미디어넷, 추후 공연 불참 통보 허경환, 김호중 술자리 동석 의혹에 \"저 아니에요\" 최주성 황재하 기자 = 음주 운전과 뺑소니 의혹을 받는 가수 김호중(33)이 연이틀 입장을 밝혔다. 김호중의","link":"https://m.entertain.naver.com/now/article/001/0014695434","retrieved":1716117457757},{"title":"\"죄는 내가 지어\"… 김호중, 창원 2일차 공연서도 사과 (네이버 TV연예 ─ 최신뉴스 ─ 뮤직)","contents":"김호중(사진=이데일리DB) 가수 김호중이 전국투어 콘서트 창원 둘째날 공연에서도 관객들에게 사과했다. 19일 가요계에 따르면 김호중은 이날 경남 창원에서 열린 ‘트바로티 클래식 아레나 투어 2024’ 창원 2일차 공","link":"https://m.entertain.naver.com/now/article/018/0005743498","retrieved":1716117457757},{"title":"김호중, 김천 콘서트 무산되나…SBS미디어넷 '공연 연출' 불참 (네이버 TV연예 ─ 최신뉴스 ─ 뮤직)","contents":"뺑소니 혐의에 음주운전 의혹도 더해진 트로트 가수 김호중(33)이 경남 창원 콘서트를 강행한 데 이어 경북 김천 공연은 무산될 위기에 처했다. 19일 업계에 따르면, SBS미디어넷은 김호중이 오는 6월 1∼2일 경북","link":"https://m.entertain.naver.com/now/article/003/0012554196","retrieved":1716117457757},{"title":"[강일홍의 클로즈업] '살아있길 잘했어'...서정희의 '희로애락' (네이버 TV연예 ─ 최신뉴스 ─ 연예가화제)","contents":"\"절대 다시 일어설 수 없다는 사람들에게\" 던지는 메시지 일상과 삶을 되돌아 본 에세이집 '살아있길 잘했어' 출간 인생은 희로애락, 기쁨과 즐거움만 있는 게 아니라 걱정과 슬픔이 늘 공존합니다. 생각하기에 따라 차이","link":"https://m.entertain.naver.com/now/article/629/0000289048","retrieved":1716131571054},{"title":"김호중 열흘만에 음주운전 시인...팬카페에도 글 남겨\"아리스 식구들의 자존심에 큰 상처를 드려 죄송하다”\" (네이버 TV연예 ─ 최신뉴스 ─ 연예가화제)","contents":"가수 김호중이 사고 열흘 만에 음주운전 사실을 시인했다. 김호중은 19일 창원 공연을 마친 뒤 소속사 생각엔터테인먼트를 통해 \"저는 음주운전을 했다\"며 \"크게 후회하고 반성하고 있다. 경찰 조사에 성실히 임하겠다\"고","link":"https://m.entertain.naver.com/now/article/396/0000676781","retrieved":1716131571056},{"title":"'음주운전' 김호중, 팬카페에 심경글 \"죄지은 사람, 내 모습 싫어\" (네이버 TV연예 ─ 최신뉴스 ─ 연예가화제)","contents":"가수 김호중이 음주운전을 시인하고 팬들에게 심경을 전했다. 김호중은 19일 공식 팬카페에 '죄송합니다'라는 제목의 글을 통해 \"술을 한잔이라도 입에 대면 핸들을 잡으면 안 된다는 것을 잘 알고 있다\"고 밝혔다. 그는","link":"https://m.entertain.naver.com/now/article/108/0003236563","retrieved":1716131571056},{"title":"콘서트 끝나니 이제야…김호중, 열흘만 음주운전 인정 \"크게 후회하고 반성\" [종합] (네이버 TV연예 ─ 최신뉴스 ─ 연예가화제)","contents":"음주운전을 완강히 부인하던 가수 김호중이 사고 열흘 후에야 음주운전을 인정했다. 김호중 소속사 생각엔터테인먼트 측은 19일 \"자사 아티스트 김호중 논란과 더불어 당사의 잘못된 판단으로 사회적 물의를 일으킨 점 고개","link":"https://m.entertain.naver.com/now/article/076/0004146591","retrieved":1716131571056},{"title":"\"60살 넘었는데..\" 최화정, 유튜브 도전 성공→결국 눈물 [종합] (네이버 TV연예 ─ 최신뉴스 ─ 연예가화제)","contents":"방송인 최화정이 팬들의 사랑에 눈물을 보였다. 18일 유튜브 채널 '안녕하세요 최화정이에요'에는 '신기한 것들이 쏟아지는 최화정 에르메스백'이라는 제목의 영상이 공개됐다. 공개된 영상 속 최화정은 SBS 파워FM '","link":"https://m.entertain.naver.com/now/article/108/0003236562","retrieved":1716131571056},{"title":"'공연 강행' 김호중, 음주·뺑소니 결국 직접 시인…열흘 간 '대중 기만'(종합) (네이버 TV연예 ─ 최신뉴스 ─ 연예가화제)","contents":"가수 김호중이 결국 음주 및 뺑소니 운전을 시인했다. 김호중과 소속사는 사고 직후부터 \"술을 마시지 않았다\"란 입장을 보이며 콘서트까지 강행했기에, 이들에 대한 비판은 더욱 거세지고 있다. 김호중은 19일 오후 소속","link":"https://m.entertain.naver.com/now/article/421/0007548467","retrieved":1716131571056},{"title":"'음주운전 인정' 김호중 \"죄지은 사람이 말 길면 뭐하겠냐\" 심경 [전문] (네이버 TV연예 ─ 최신뉴스 ─ 연예가화제)","contents":"트로트 가수 김호중이 사고 열흘 만에야 음주운전을 인정한 가운데, 팬카페에 심경글을 남겼다. 김호중은 19일 뒤늦게 음주운전을 인정했다. 김호중 소속사 생각엔터테인먼트 측은 19일 \"\"자사 아티스트 김호중 논란과 더","link":"https://m.entertain.naver.com/now/article/076/0004146590","retrieved":1716127922731},{"title":"\"배우업계 불황\" 이동건, 2억 대출→카페 창업 도전 '母는 반대' ('미우새')[종합] (네이버 TV연예 ─ 최신뉴스 ─ 연예가화제)","contents":"'미우새' 이동건이 제주에서 카페를 창업하고 싶다는 목표를 드러냈다. 19일 방송된 SBS '미운 우리 새끼'에서는 이동건이 제주도 카페 창업에 도전하는 모습이 깜짝 공개됐다. 이날, 이동건은 긴장한 얼굴로 은행을","link":"https://m.entertain.naver.com/now/article/076/0004146588","retrieved":1716127922737},{"title":"김호중, 음주운전 인정 “잘못된 판단 후회하고 반성...경찰 조사 성실히 임할 터”(공식입장 전문) (네이버 TV연예 ─ 최신뉴스 ─ 연예가화제)","contents":"가수 김호중이 결국 음주운전 사실을 인정했다. 김호중 소속사 생각엔터테인먼트 측은 19일 “김호중 논란과 더불어 당사의 잘못된 판단으로 사회적 물의를 일으킨 점 고개 숙여 사과드린다. 최초 공식 입장에서부터 지금까지","link":"https://m.entertain.naver.com/now/article/057/0001818531","retrieved":1716127922737},{"title":"[종합]김호중, 사고 10일 만에 결국 음주운전 인정…\"숨기기 급급\"(전문) (네이버 TV연예 ─ 최신뉴스 ─ 연예가화제)","contents":"가수 김호중의 뺑소니 사고 당일 음주운전을 했다고 인정했다. 김호중은 19일 \"저는 음주 운전을 했다\"라며 \"크게 후회하고 반성한다\"라는 사과문을 전했다. 김호중은 지난 9일 오후 11시40분쯤 강남구 압구정동 한","link":"https://m.entertain.naver.com/now/article/076/0004146587","retrieved":1716127922737},{"title":"김호중, 음주운전 인정 “크게 후회하고 반성...실망감 드려 죄송하다”(공식입장 전문) (네이버 TV연예 ─ 최신뉴스 ─ 연예가화제)","contents":"가수 김호중이 음주운전 사실을 인정했다. 김호중 소속사 생각엔터테인먼트 측은 19일 “김호중 논란과 더불어 당사의 잘못된 판단으로 사회적 물의를 일으킨 점 고개 숙여 사과드린다. 최초 공식 입장에서부터 지금까지 상황","link":"https://m.entertain.naver.com/now/article/410/0000999412","retrieved":1716127922737},{"title":"“어리석었다”…김호중, 음주운전 심경 (네이버 TV연예 ─ 최신뉴스 ─ 연예가화제)","contents":"가수 김호중이 음주 운전을 시인하며 심경을 전했다. 19일 김호중은 공식 팬카페를 통해 “술을 한 잔이라도 입에 대면 핸들을 잡으면 안 된다라는 것을 너무나도 잘 알고 있다”며 “저의 어리석은 판단으로 인해 이렇게","link":"https://m.entertain.naver.com/now/article/396/0000676780","retrieved":1716127922737},{"title":"김호중, 결국 음주운전 인정 (네이버 TV연예 ─ 최신뉴스 ─ 연예가화제)","contents":"음주 뺑소니 의혹을 받는 가수 김호중(33)이 결국 음주운전 사실을 인정했다. 김호중은 19일 소속사 생각엔터테인먼트를 통해 밝힌 입장문에서 “저는 음주운전을 하였다”며 “크게 후회하고 반성하고 있다. 경찰 조사에","link":"https://m.entertain.naver.com/now/article/009/0005305499","retrieved":1716127922738},{"title":"'음주 뺑소니 인정' 김호중 \"조사 끝나면 돌아오겠다\" (네이버 TV연예 ─ 최신뉴스 ─ 연예가화제)","contents":"음주운전 뺑소니를 인정한 김호중(33)이 벌써 돌아올 날을 기약하고 있다. 김호중은 10일 소속사 생각엔터테인먼트서 공식입장을 내기 15 분 전 자신의 팬카페애 '진심으로 이번 일에 대해 우리 아리스(팬덤명) 식구들","link":"https://m.entertain.naver.com/now/article/437/0000393329","retrieved":1716127922738},{"title":"김호중 \"음주운전 인정\"…소속사 \"상황 숨기기에 급급했다\" (네이버 TV연예 ─ 최신뉴스 ─ 연예가화제)","contents":"“저는 음주운전을 하였습니다. 고개 숙여 사과드립니다.” 뺑소니 혐의로 수사를 받고 있는 트로트 가수 김호중씨(33)가 결국 음주운전을 인정했다. 김씨의 소속사 생각엔터테인먼트는 19일 입장문을 통해 “자사 아티스트","link":"https://m.entertain.naver.com/now/article/277/0005420125","retrieved":1716127922738},{"title":"김호중, 음주운전 시인…“후회하고 반성” (네이버 TV연예 ─ 최신뉴스 ─ 연예가화제)","contents":"뺑소니 혐의로 입건된 가수 김호중이 음주운전을 시인했다. 19일 소속사 생각엔터테인먼트 측은 “김호중 논란과 더불어 당사의 잘못된 판단으로 사회적 물의를 일으킨 점 고개 숙여 사과드린다”며 “최초 공식 입장에서부터","link":"https://m.entertain.naver.com/now/article/396/0000676779","retrieved":1716127922739},{"title":"\"저는 음주운전을 했습니다\" 김호중 결국 인정…\"크게 후회하고 반성\"[전문] (네이버 TV연예 ─ 최신뉴스 ─ 연예가화제)","contents":"“저는 음주운전을 하였습니다.” 가수 김호중이 음주운전 사실을 인정하고 사과했다. 김호중은 19일 오후 10시 넘어 소속사 생각엔터테인먼트를 통해 음주운전 시인을 포함한 사과문을 냈다. 김호중은 “저의 한순간의 잘못","link":"https://m.entertain.naver.com/now/article/241/0003351276","retrieved":1716127917418},{"title":"“난리났네”…티아라, 15주년 맞아 뭉쳤다 (네이버 TV연예 ─ 최신뉴스 ─ 연예가화제)","contents":"사진=지연 인스타그램 그룹 티아라가 뭉쳤다. 19일 지연은 자신의 SNS를 통해 하트 이모티콘과 함께 두 장의 사진을 게재했다. 공개된 사진에는 완전체로 뭉친 티아라의 모습이 담겼다. 함은정·큐리·효민·지연은 맨투맨","link":"https://m.entertain.naver.com/now/article/396/0000676778","retrieved":1716127922739},{"title":"'유명가수와 길거리 심사단' 마지막 음원 발매…'벌써 일년' 포함 (네이버 TV연예 ─ 최신뉴스 ─ 연예가화제)","contents":"전국의 길거리 심사위원단이 '싱어게인3' TOP 7의 무대를 직접 심사하는 신개념 로드 버스킹 쇼 프로그램 JTBC '유명가수와 길거리 심사단'의 EP.10 음원이 지난 16일 공개됐습니다. EP.10에는 EJel(","link":"https://m.entertain.naver.com/now/article/057/0001818527","retrieved":1716127922741},{"title":"'돌싱父' 최민환 \"母가 삼남매 케어, 없었다면 활동 꿈도 못 꿨을 것\" ('슈돌')[종합] (네이버 TV연예 ─ 최신뉴스 ─ 연예가화제)","contents":"'슈돌' 최민환이 삼남매 육아를 도와주는 엄마에게 고마운 마음을 드러냈다. 19일 방송된 KBS2 예능프로그램 '슈퍼맨이 돌아왔다'에서는 삼남매와 최민환의 일상이 공개됐다. 최민환과 삼남매는 오랜만에 놀이터에서 여유","link":"https://m.entertain.naver.com/now/article/076/0004146584","retrieved":1716127922743},{"title":"\"저 아니에요\" 허경환 이어 슬리피도..김호중 술자리 동석 루머 부인 (네이버 TV연예 ─ 최신뉴스 ─ 연예가화제)","contents":"코미디언 허경환에 이어 가수 슬리피가 '음주 뺑소니' 의혹을 받는 김호중과 유흥주점에 함께 있었다는 소문에 대해 일축했다. 슬리피는 19일 자신의 인스타그램 스토리에 \"그..저 아니예요. 다들 신경 써주셔서 감사합니","link":"https://m.entertain.naver.com/now/article/108/0003236558","retrieved":1716127922746},{"title":"[공식] 김호중, 결국 음주운전 인정…\"후회하고 반성해\" (전문) (네이버 TV연예 ─ 최신뉴스 ─ 연예가화제)","contents":"뺑소니 혐의를 받는 가수 김호중(33)이 음주운전 사실을 뒤늦게 인정했다. 소속사 생각엔터테인먼트는 19일 공식입장을 통해 \"자사 아티스트 김호중 논란과 더불어 당사의 잘못된 판단으로 사회적 물의를 일으킨 점 고개","link":"https://m.entertain.naver.com/now/article/076/0004146583","retrieved":1716127922749},{"title":"[이슈]끝까지 돈에 눈 멀고 팬 기만… 김호중 악마의 인성 (네이버 TV연예 ─ 최신뉴스 ─ 연예가화제)","contents":"악마도 울고 갈 인성이다. 김호중이 음주운전 뺑소니를 인정했다. 사건 발생 열흘 만이며 콘서트가 끝난 직후 발표다. 김호중 소속사 생각엔터테인먼트는 19일 오후 10시 '자사 아티스트 김호중 논란과 더불어 당사의 잘","link":"https://m.entertain.naver.com/now/article/437/0000393328","retrieved":1716127922750},{"title":"김호중 \"음주 운전한 것 맞다…한순간의 잘못된 판단\" 시인 (네이버 TV연예 ─ 최신뉴스 ─ 연예가화제)","contents":"가수 김호중이 음주 운전을 시인했다. 김호중은 19일 밤 소속사 생각엔터테인먼트를 통해 \"죄송합니다, 김호중입니다\"라며 \"저의 한순간의 잘못된 판단이 많은 분께 상처와 실망감을 드려 진심으로 죄송하다는 사과의 말을","link":"https://m.entertain.naver.com/now/article/421/0007548460","retrieved":1716127922751},{"title":"음주 아니라며 공연 강행하던 김호중...결국 음주 인정[공식] (네이버 TV연예 ─ 최신뉴스 ─ 연예가화제)","contents":"김호중이 결국 스스로 음주 운전을 인정했다. 19일 소속사 생각엔터테인먼트는 김호중 음주운전 혐의 관련 공식입장을 발표했다. 먼저 소속사는 \"자사 아티스트 김호중 논란과 더불어 당사의 잘못된 판단으로 사회적 물의를","link":"https://m.entertain.naver.com/now/article/445/0000197987","retrieved":1716127922752},{"title":"“이혼 임박” 제니퍼 로페즈, 벤 애플렉과 결별 수순 “전문 변호사 고용”[해외이슈](종합) (네이버 TV연예 ─ 최신뉴스 ─ 해외연예)","contents":"세계적 가수 제니퍼 로페즈(54)와 ‘배트맨’ 벤 애플렉(51)의 이혼이 임박했다. 한 소식통은 18일(현지시간) ‘인 터치’에 \"로페즈는 애플렉과 이혼하기 위해 “위기를 관리하는 홍보 전문가를 고용했다”고 보도했다","link":"https://m.entertain.naver.com/now/article/117/0003833375","retrieved":1716124523653},{"title":"퍼프 대디, 호텔서 전 연인 폭행한 영상 파문…걷어차고 끌고가 [N해외연예] (네이버 TV연예 ─ 최신뉴스 ─ 해외연예)","contents":"미국 힙합계 거물로 통하는 퍼프 대디(션 디디 콤스)가 전 연인인 가수 캐시 벤트라를 폭행하는 영상이 공개됐다. 미국 CNN은 18일(현지 시간) 퍼프 대디가 지난 2016년 연인이었던 캐시 벤트라를 폭행하는 CCT","link":"https://m.entertain.naver.com/now/article/421/0007548390","retrieved":1716113707579},{"title":"리애나, 일상복도 힙하게…트레이닝 점프 슈트 '스타일리시' [N해외연예] (네이버 TV연예 ─ 최신뉴스 ─ 해외연예)","contents":"팝스타 리애나(리한나)가 힙한 일상 패션을 선보였다. 미국 연예 매체 스플래시 닷컴은 19일(한국 시간) 리애나가 미국 뉴욕의 한 호텔을 체크아웃한 후 나서는 모습을 포착했다. 리애나는 트레이닝복 점프슈트를 입고 긴","link":"https://m.entertain.naver.com/now/article/421/0007548352","retrieved":1716110056585},{"title":"‘배드보이’ 닉값 제대로… 여친 뒷목잡고 바닥에 내동댕이, 발길질한 래퍼 (네이버 TV연예 ─ 최신뉴스 ─ 해외연예)","contents":"미국 힙합계 거물 퍼프 대디(션 디디 콤스, Sean John Combs)가 전 연인 미국 R&amp;B 가수 캐시를 폭행하는 영상이 8년 만에 공개됐다. CNN은 18일(현지시간) 단독으로 입수한 CCTV 영상을 공개했다","link":"https://m.entertain.naver.com/now/article/396/0000676753","retrieved":1716110056587},{"title":"벤 애플렉, 결혼 반지 뺐다..'20년만 재결합' 제니퍼 로페즈와 이혼? [Oh!llywood] (네이버 TV연예 ─ 최신뉴스 ─ 해외연예)","contents":"배우 벤 애플렉과 제니퍼 로페즈 부부의 이혼이 공식화 됐다. 이혼 위기 속 벤 애플렉이 결혼반지를 빼고 외출한 모습이 포착된 것. 18일 페이지 식스는 벤 애플렉이 아내 제니퍼 로페즈와 이혼 루머 속 처음으로 결혼","link":"https://m.entertain.naver.com/now/article/109/0005079744","retrieved":1716106661067},{"title":"'걸그룹' 센터 멤버, 남자 배우 여러명과 '바람'...충격 폭로 나왔다 [룩@재팬] (네이버 TV연예 ─ 최신뉴스 ─ 해외연예)","contents":"일본 방송인 겸 정치인 히가시 고쿠마루 히데오가 한 아이돌 그룹과 관련된 깜짝 폭로를 해 눈길을 끈다. 16일(현지 시간) 배우 겸 개그맨 미야사코 히로유키(54)가 자신의 유튜브 채널에 \"연예계 BIG3와 프리 토","link":"https://m.entertain.naver.com/now/article/213/0001295574","retrieved":1716102922027},{"title":"“결혼반지 뺐다” 벤 애플렉, 제니퍼 로페즈와 이혼 공식화?[해외이슈] (네이버 TV연예 ─ 최신뉴스 ─ 해외연예)","contents":"벤 애플렉(51)이 결혼 반지를 뺐다. 제니퍼 로페즈(54)와 이혼이 공식화되는 분위기라는 주장이 나오고 있다. 페이지식스는 18일(현지시간) “벤 애플렉이 운전 중 왼손을 들어올리는 모습이 포착됐다”면서 “그는 결","link":"https://m.entertain.naver.com/now/article/117/0003833248","retrieved":1716086230293},{"title":"'브리저튼3' 니콜라 코클란 \"출연료 17만 원 받던 나...30대 되고 터졌다\" [할리웃통신] (네이버 TV연예 ─ 최신뉴스 ─ 해외연예)","contents":"넷플릭스 시리즈 '브리저튼'으로 전 세계의 주목을 받은 배우 니콜라 코클란(37)이 과거 경제적인 어려움을 겪었다고 고백해 눈길이 쏠렸다. 16일(현지 시간), 잡지 '마리끌레르'가 배우 니콜라 코클란과 진행한 인터","link":"https://m.entertain.naver.com/now/article/213/0001295565","retrieved":1716080526685},{"title":"여친 내동댕이 치고 발길질까지…힙합거물 폭행 영상 '파장' (네이버 TV연예 ─ 최신뉴스 ─ 해외연예)","contents":"'퍼프 대디(Puff Daddy)'로 통하는 미국 힙합계의 거물 션 디디 콤스(55·Sean John Combs)가 8년 전 전 여자친구인 미국 R&amp;B 가수 캐시를 과도하게 폭행하는 장면이 담긴 영상이 공개돼 파장이","link":"https://m.entertain.naver.com/now/article/003/0012553298","retrieved":1716073969079},{"title":"힙합거물 콤스 8년전 여자친구 캐시 폭행 영상 공개돼 파문 (네이버 TV연예 ─ 최신뉴스 ─ 해외연예)","contents":"공소시효 지나 형사기소 불가…캐시는 작년 11월 민사 제소했다 합의 임미나 특파원 = '퍼프대디'라는 예명으로 유명한 미국 힙합계의 거물 션 디디 콤스(54)가 8년 전에 여자친구인 가수 캐시(본명 카산드라 벤투라)","link":"https://m.entertain.naver.com/now/article/001/0014694324","retrieved":1716063292208},{"title":"걸그룹 험프백, 멤버 전원 동시 '임신'했다...활동 중단 [룩@재팬] (네이버 TV연예 ─ 최신뉴스 ─ 해외연예)","contents":"활동을 중단한 일본 밴드 험프 백이 활동 복귀를 선언하며, 최근 멤버 전원이 출산했다고 공개했다. 16일(현지 시간), 일본 3인조 밴드 험프 백(Hump Back)이 소셜네트워크서비스를 통해 출산과 활동 복귀 계획","link":"https://m.entertain.naver.com/now/article/213/0001295556","retrieved":1716038024430},{"title":"‘가오갤’ 토니 맥파르, 47세에 돌연 사망‥크리스 프랫 “큰 충격” (네이버 TV연예 ─ 최신뉴스 ─ 해외연예)","contents":"영화 ‘가디언즈 오브 갤럭시’에서 할리우드 배우 크리스 프랫과 호흡을 맞췄던 스턴트맨 토니 맥파르가 세상을 떠났다. 향년 47세. 크리스 프랫은 지난 5월 16일(이하 현지 시간) 자신의 소셜미디어에 “친구이자 스턴","link":"https://m.entertain.naver.com/now/article/609/0000855146","retrieved":1716030732325},{"title":"'남녀 성폭행 혐의' 美 힙합 갑부, 전 여친 폭행 영상까지 공개 \"적나라\"[할리웃통신] (네이버 TV연예 ─ 최신뉴스 ─ 해외연예)","contents":"미국의 유명 래퍼 퍼프 대디(디디, 션 존 콤스)가 전 여자 친구 폭행으로 또 다시 구설에 올랐다. 최근 퍼프 대디는 성매매, 성폭행 등 각종 범죄 혐의로 물의를 빚은 바 있다. 17일(현지시간) CNN은 미국 로스","link":"https://m.entertain.naver.com/now/article/213/0001295551","retrieved":1716030732327},{"title":"배우 장가윤 \"매일 유서 작성\"...이혼 후 심리적으로 불안해 보인다 [룩@차이나] (네이버 TV연예 ─ 최신뉴스 ─ 해외연예)","contents":"중국 배우 장가윤(小??·샤오톈톈)이 정서적으로 매우 불안해보인다. 장가윤이 매일 같이 유서를 작성해 오고 있다고 고백해 많은 이들을 충격에 빠뜨렸다. 지난 8일(현지 시간), 중국 예능 프로그램 '소명성대근반'(小","link":"https://m.entertain.naver.com/now/article/213/0001295548","retrieved":1716027246652},{"title":"구준엽 아내 서희원, 마약 루머 마침표 찍었다… “무죄 밝혀준 검찰에 감사” (네이버 TV연예 ─ 최신뉴스 ─ 해외연예)","contents":"쉬시위안과 구준엽/출처=보그 타이완 그룹 클론 구준엽 아내이자 대만 톱배우 서희원(徐熙媛·쉬시위안)이 마약 혐의 의혹에서 완전히 벗어났다. 쉬시위안은 지난 17일 자신의 사회관계망서비스(SNS)에 현지 매체의 마약","link":"https://m.entertain.naver.com/now/article/022/0003933985","retrieved":1716023620008},{"title":"美 힙합 거물 퍼프대디, 호텔서 여친 폭행하는 영상 ‘충격’ [할리웃톡] (네이버 TV연예 ─ 최신뉴스 ─ 해외연예)","contents":"퍼프 대디. 로이터 미국 유명 래퍼이자 힙합계 거물 퍼프대디(본명 션 존 콤스, 디디)가 전 여자친구를 폭행하는 영상이 공개돼 충격을 안겼다. 17일(현지시간) CNN은 단독으로 입수한 CCTV 영상을 공개했다. 보","link":"https://m.entertain.naver.com/now/article/468/0001061207","retrieved":1716023620010},{"title":"'20년만 재결합' 제니퍼 로페즈 벤 애플렉, 결혼 2년만에 이혼 위기 (종합)[Oh!llywood] (네이버 TV연예 ─ 최신뉴스 ─ 해외연예)","contents":"가수 겸 배우 제니퍼 로페즈와 배우 겸 감독 벤 애플렉이 이혼 위기를 겪고 있는 것으로 전해졌다. 페이지식스의 17일(현지시간) 보도에 따르면 부동산 업계에서는 애플렉이 미국 LA에서 새 집을 찾고 있다는 소문이 떠","link":"https://m.entertain.naver.com/now/article/109/0005079156","retrieved":1716023620010},{"title":"여자친구 던지고 발길질, 힙합 거물 폭행 영상 ‘충격’ [할리우드비하인드] (네이버 TV연예 ─ 최신뉴스 ─ 해외연예)","contents":"퍼프 대디(본명 션 존 콤스, 디디)의 폭행 영상이 공개돼 충격을 주고 있다. CNN은 5월 17일(현지시간) 단독으로 입수한 CCTV 영상을 공개했다. 해당 영상은 2016년 3월 미국 LA 한 호텔에서 녹화된 C","link":"https://m.entertain.naver.com/now/article/609/0000855113","retrieved":1716020082547},{"title":"제니퍼 로페즈, 20년 만에 결혼한 벤 애플렉과 이혼하나...이별 게시물에 '좋아요' [할리웃통신] (네이버 TV연예 ─ 최신뉴스 ─ 해외연예)","contents":"할리우드 배우 벤 애플렉(51), 제니퍼 로페즈(54) 부부의 불화설이 제기된 가운데 제니퍼 로페즈가 의미심장한 게시물에 '좋아요'를 눌러 대중의 관심을 끌고 있다. 16일(현지 시간), 외신 매체 '데일리메일'이","link":"https://m.entertain.naver.com/now/article/213/0001295535","retrieved":1716009283557},{"title":"\"6세 아들과 목욕탕 못 가 슬프다\"...女방송인 글에 누리꾼 갑론을박 [룩@재팬] (네이버 TV연예 ─ 최신뉴스 ─ 해외연예)","contents":"일본 방송인 마루아카 이즈미(52)가 6세 아들과 혼욕을 하지 못하는 것에 대한 섭섭함을 토로했는데, 이와 관련해 소셜네트워크서비스에서는 갑론을박이 일었다. 지난 13일(현지 시간), 방송인 마루아카 이즈미는 소셜네","link":"https://m.entertain.naver.com/now/article/213/0001295532","retrieved":1716002157057},{"title":"'구준엽♥' 서희원, 마약 의혹 벗었다…\"무죄 밝혀준 검찰에 감사\" (네이버 TV연예 ─ 최신뉴스 ─ 해외연예)","contents":"그룹 클론 구준엽 아내이자 대만 인기 배우 쉬시위안(서희원)이 마약 의혹을 벗은 심경을 전했다. 쉬시위안은 지난 17일 자신의 인스타그램에 마약 의혹을 벗었다는 내용의 기사를 캡처해 게재한 뒤 \"우리 무죄를 밝혀준","link":"https://m.entertain.naver.com/now/article/421/0007546892","retrieved":1716002157057},{"title":"배우 켈 미첼 \"전처가 낙태한 아이, 내 애 아니었다\"...충격 폭로 [할리웃통신] (네이버 TV연예 ─ 최신뉴스 ─ 해외연예)","contents":"미국 배우 켈 미첼이 전처인 배우 티샤 햄튼의 부정행위를 폭로한 가운데 티샤 햄튼도 반박에 나섰다. 16일(현지 시간), 팟 캐스트 '클럽 셰이 셰이'(Club Shay Shay)에 출연한 배우 켈 미첼이 전처 티샤","link":"https://m.entertain.naver.com/now/article/213/0001295528","retrieved":1715999261103},{"title":"'가오갤' 토니 맥파르, 47세에 사망...사인 불명 [할리웃통신] (네이버 TV연예 ─ 최신뉴스 ─ 해외연예)","contents":"배우 크리스 프랫의 스턴트 더블 토니 맥파르가 별세했다. 향년 47세. 16일(현지 시간) 크리스 프랫은 자신의 소셜네트워크서비스 스토리 기능(24시간만 열람할 수 있는 게시물)을 통해 토니 맥파르의 사망 소식을 알","link":"https://m.entertain.naver.com/now/article/213/0001295527","retrieved":1715997277712},{"title":"휴 그랜트도 1억원 기부한 英 자선가…알고보니 미담 조작 '파파괴' (네이버 TV연예 ─ 최신뉴스 ─ 해외연예)","contents":"유명 영국 배우 휴 그랜트가 약 7만5000파운드(약 1억3000만원)를 기부해 온 영국의 유명 자선단체의 설립자가 사실은 파도 파도 괴담이 드러나는 '파파괴' 인물이었다고 영국 BBC가 16일(현지시간)과 17일","link":"https://m.entertain.naver.com/now/article/421/0007546481","retrieved":1715958957488},{"title":"'세기의 재결합' 제니퍼 로페즈♥︎벤 애플렉, 결혼 2년만에 별거..결별설 제기 [Oh!llywood] (네이버 TV연예 ─ 최신뉴스 ─ 해외연예)","contents":"배우 제니퍼 로페즈(54)와 벤 애플렉(51)의 결별설이 제기됐다. 최근 두 사람이 별거한다는 보도가 페이지식스 등 외신을 통해 전해진 가운데 로페즈는 16일(현지시간) '깨진 관계'에 대한 SNS 게시물에 좋아요를","link":"https://m.entertain.naver.com/now/article/109/0005078762","retrieved":1715951790258}]}