{"title":"다음 연예 ─ 뉴스 ─ 스타","url":"https://entertain.daum.net/news/star","favicon":"https://entertain.daum.net/news/favicon.ico","elements":[{"title":"'로컬식탁' 여수&부산 핫 플레이스 한 번에 몰아보기","contents":"‘로컬식탁’이 여수와 부산의 핫한 여행지를 한 번에 몰아보는 특별판 ‘세끼 투어 여수 VS 부산’으로 시청자를 찾는다. 14일(오늘) 밤 10시 30분 방송되는 MBC 미식 인문학 토크쇼 ‘로컬식탁’ 특별판에서는 이상민, 하석진을 필두로 배성재, 주우재와 함께 랜선 ‘세끼 투어’를 떠난다. 첫 번째 대결은 바로 ‘빨간 맛’으로, 전라남도 여수의 ‘빨간","link":"https://entertain.v.daum.net/v/20220314095527258","retrieved":1647219386427},{"title":"김남길X서현X유재명X이현욱X이호정, 넷플릭스 '도적:칼의소리' 캐스팅","contents":"[OSEN=최나영 기자]&nbsp;세계적인 엔터테인먼트 스트리밍 서비스 넷플릭스(Netflix)가 새로운 시리즈 '도적: 칼의 소리'의 제작 확정과 함께 캐스팅을 발표했다. 넷플릭스가 '나쁜 녀석들: 악의 도시', '38사기동대'의 콤비 한정훈 작가, 황준혁 감독과 손잡고 첫 시대극 '도적: 칼의 소리'를 제작한다. '도적: 칼의 소리'는 격동의 일제강점기, 각","link":"https://entertain.v.daum.net/v/20220314095324151","retrieved":1647219386428},{"title":"'기상청 사람들' 박민영, ♥송강에 비혼 선언 후 \"네가 가라 제주도\"","contents":"‘기상청 사람들’ 박민영, 송강, 윤박, 유라가 현실적 문제로 잠 못 드는 열대야를 보냈다. 지난 13일 오후 방송된 JTBC 주말드라마 ‘기상청 사람들: 사내연애 잔혹사 편’(연출 차영훈‧극본 선영‧크리에이터 글Line&amp;강은경‧제작 앤피오엔터테인먼트, JTBC스튜디오, 이하 ‘기상청 사람들’) 10회에서 연애의 전제는 결혼인 진하경(박민영 분)이 이","link":"https://entertain.v.daum.net/v/20220314094454631","retrieved":1647219386430},{"title":"'스물다섯 스물하나' 남주혁, 김태리 향한 사랑 고백","contents":"[스포츠경향] 김태리와 남주혁이 사랑 고백으로 뭉클하고 설레는 여운을 안겼다. 지난 13일 방송된 tvN 토일드라마 ‘스물다섯 스물하나’(극본 권도은/연출 정지현, 김승호/제작 화앤담픽쳐스) 10회는 수도권 가구 기준 평균 12.7%, 최고 13.7%, 전국 가구 기준 평균 10.9%, 최고 11.8%를 기록하며 수도권과 전국 모두 케이블과 종편 포","link":"https://entertain.v.daum.net/v/20220314093744416","retrieved":1647219386431},{"title":"'스물다섯 스물하나' 김태리X남주혁, 소망 응원..애틋한 '영원 다짐'","contents":"‘스물다섯 스물하나’ 김태리와 남주혁이 서로의 소망을 응원했다. 지난 13일 오후 방송된 tvN 주말드라마 ‘스물다섯 스물하나’(연출 정지현, 김승호‧극본 권도은‧제작 화앤담픽쳐스) 10회는 수도권 가구 기준 평균 12.7%, 최고 13.7%, 전국 가구 기준 평균 10.9%, 최고 11.8%를 기록하며 수도권과 전국 모두 케이블과 종편 포함 동시간대","link":"https://entertain.v.daum.net/v/20220314093326212","retrieved":1647219386434},{"title":"고두심 아들 김정환 \"아버지가 엄마 사진 늘 가지고 다녔다\"","contents":"[스포츠조선 정빛 기자] '엄마의 여행 고두심이 좋아서(이하 '고두심이 좋아서') 배우 고두심이 아들 김정환과 행복한 시간을 보냈다. 13일 방송된 LG헬로비전-채널A 공동제작 '고두심이 좋아서'에서는 첫 여행지 제주에서 여행을 즐기는 고두심의 모습이 그려졌다. 고두심은 여행 시작부터 \"얼마 만에 혼자 여행을 떠나는 건지 너무 설렌다. 바다","link":"https://entertain.v.daum.net/v/20220314093312198","retrieved":1647219386437},{"title":"넷플릭스, '도적: 칼의 소리' 제작 확정..\"김남길X서현 등 출연\"","contents":"[마이데일리 = 김나라 기자] 세계적인 엔터테인먼트 스트리밍 서비스 넷플릭스가 새 오리지널 시리즈 '도적: 칼의 소리' 제작 확정과 함께 캐스팅 라인업을 발표했다. 넷플릭스는 14일 \"드라마 '나쁜 녀석들: 악의 도시' '38사기동대'의 콤비 한정훈 작가, 황준혁 감독과 손잡고 첫 시대극 '도적: 칼의 소리'를 제작한다\"라고 밝혔다. '도적: 칼의 소리","link":"https://entertain.v.daum.net/v/20220314093012055","retrieved":1647219386445},{"title":"박군, 장미 한송이 들고 한영에 \"결혼해줘\"","contents":"[동아닷컴]  SBS ‘미운우리새끼’가 박군♥한영의 깜짝 결혼 소식으로 화제를 모았다. 닐슨 코리아에 따르면, 13일 방송된 SBS ‘미운우리새끼’는 평균 가구 시청률 15.9%(수도권 기준), 화제성과 경쟁력 지표인 2049 타깃 시청률 5.2%, 분당 최고 시청률 19.3%로, 2049 및 가구시청률에서 일요 예능 1위를 기록했다. 이날은 무엇보다","link":"https://entertain.v.daum.net/v/20220314092806952","retrieved":1647219386445},{"title":"'악의 마음' 진선규 \"감개무량하다, 소름 돋았다\"","contents":"[스포츠경향] “내가? 이런 지적인 역할을?” “어느새 캐릭터는 마치 내 몸에 맞춰 만든 옷처럼 꼭 맞게 되었죠” 배우 진선규의 첫 드라마 주연작인‘악의 마음을 읽는 자들’이 묵직한 울림을 남기고 막을 내렸다. 지난 12일 SBS 금·토드라마 ‘악의 마음을 읽는 자들’이 종영했다. 한국형 프로파일링의 태동을 치밀하게, 과감하고 깊이 있게 그리며","link":"https://entertain.v.daum.net/v/20220314092743945","retrieved":1647219386446},{"title":"'결사곡3' 박주미, 진격의 연하남 부배와 입맞춤","contents":"[스포츠경향] 박주미를 향한 부배의 파워 직진이 시작됐다. 지난 13일(일) 밤 9시에 방송된 TV CHOSUN 주말미니시리즈 ‘결혼작사 이혼작곡3’(극본 피비(Phoebe, 임성한)/연출 오상원, 최영수 /제작 하이그라운드, ㈜지담 미디어, 초록뱀 미디어/이하 ‘결사곡3’) 6회분은 닐슨코리아 기준 전국 시청률 7.9%, , 분당 최고 시청률은 8","link":"https://entertain.v.daum.net/v/20220314092557870","retrieved":1647219386446},{"title":"고두심 아들 김정환 공개, 훈남 비주얼 배우","contents":"[동아닷컴] 고두심 아들 김정환 공개, 훈남 비주얼 배우 [TV북마크] 배우 고두심이 생애 첫 단독 MC를 맡아 화제를 모은 ‘엄마의 여행 고두심이 좋아서(이하 ‘고두심이 좋아서’)가 첫 방송됐다. 어제(13일) 방송된 LG헬로비전-채널A 공동제작 ‘고두심이 좋아서’에서는 첫 여행지 제주에서 여행을 즐기는 고두심의 모습이 그려졌다. 여행 시작부터 \"얼마","link":"https://entertain.v.daum.net/v/20220314092552868","retrieved":1647219386446},{"title":"'1박2일' 新멤버 나인우, 초긍정 캐릭터 벌써 정착..사상 초유 '제작진 벌칙' 엔딩 '훈훈'","contents":"[스포츠조선 고재완 기자] KBS2 '1박 2일'이 여섯 남자의 심장 쫄깃한 승부로 안방극장에 꽉 찬 에너지를 선사했다. 13일 방송 '등 따시고 배부른 거제' 특집 마지막 이야기는 시청률 12%(이하 닐슨코리아 집계, 전국 가구 기준)를 기록했다. 특히 홀로 3kg 멸치 똥 따기에 돌입한 김종민 앞에 문세윤과 연정훈이 재등장, \"도와드릴까요","link":"https://entertain.v.daum.net/v/20220314092130700","retrieved":1647219386446},{"title":"'싱어게인2' 제작진 \"아쉬움 있었지만 배울 점도 많았죠\"","contents":"[티브이데일리 김종은 기자] 시즌1의 대성공 이후 쉴 틈 없이 제작된 차기 시즌. 전작의 빈틈을 메울 새도 없었다. 그렇기에 시즌2에서는 호평보단 '아쉽다'는 비판의 목소리가 더 컸던 것도 사실. 채성욱 PD와 윤현준 CP는 이런 평가에 대한 솔직한 심경을 밝혔다. 최근 종영한 JTBC 예능프로그램 '싱어게인'2는 2021년 인기리에 방송된 '싱어게인'의","link":"https://entertain.v.daum.net/v/20220314091806545","retrieved":1647219386447},{"title":"'펜하' 송회장 정아미, 신생 기획사 전속계약","contents":"[동아닷컴] ‘펜하’ 송회장 정아미, 신생 기획사 전속계약 [공식] 배우 정아미가 신생 기획사인 노아엔터테인먼트와 전속계약을 체결했다. 14일 노아엔터테인먼트 측은 “배우 정아미가 노아엔터테인먼트의 새 가족이 됐다”고 밝혔다. 오랫동안 연극무대에서 활동했던 정아미는 서울예술대학 연극과를 졸업하고 1983년 연극 ‘환도와 리스’로 데뷔했다. 그간 다수의 드","link":"https://entertain.v.daum.net/v/20220314091533451","retrieved":1647219386449},{"title":"'도적: 칼의 소리' 김남길-서현-유재명-이현욱-이호정 캐스팅","contents":"[동아닷컴] ‘도적: 칼의 소리’ 김남길-서현-유재명-이현욱-이호정 캐스팅 [공식] 넷플릭스(Netflix)가 새로운 시리즈 ‘도적: 칼의 소리’의 제작 확정과 함께 캐스팅을 발표했다. 넷플릭스가 [나쁜 녀석들: 악의 도시], [38사기동대]의 콤비 한정훈 작가, 황준혁 감독과 손잡고 첫 시대극 ‘도적: 칼의 소리’를 제작한다. ‘도적: 칼의 소리’는 격","link":"https://entertain.v.daum.net/v/20220314091333374","retrieved":1647219386451}]}