{"title":"다음 연예 ─ 뉴스 ─ 해외","url":"https://entertain.daum.net/news/abroad","favicon":"https://entertain.daum.net/news/favicon.ico","elements":[{"title":"칸예 웨스트 \"내 물건 다 태워라\"...킴 카다시안, 살벌 이혼 과정 공개","contents":"[TV리포트=안수현 기자] 래퍼 칸예 웨스트와 킴 카다시안의 이혼 과정이 온 세상에 알려졌다. 20일(현지 시간) 킴 카다시안은 방송 '카다시안 패밀리'을 통해 이혼이 확정되던 날의 모습을 적나라하게 공개했다. 그는 전남편 칸예 웨스트의 창고 중 한 곳을 청소해 이목을 모았다. 이날 킴 카다시안은 그와의 추억이 담긴 기념품을 저장하고 싶은 욕구에 대해 털어","link":"https://v.daum.net/v/20230720212030276","retrieved":1689855914962},{"title":"'58세' 배우 폴리나, 탈의 사진 공개...\"노화는 자연스러운 것\"","contents":"[TV리포트=안수현 기자] 영화배우 폴리나 포리즈코바(58)가 상반신 노출을 한 사진을 공개해 관심이 집중된다. 폴리나 포리즈코바는 자신의 소셜 네트워크 서비스 계정에 속옷만 입은 채 탄탄한 복근을 자랑하는 사진을 자주 게시한다. 최근에도 그는 노출이 있는 사진을 올려 이목을 끈 바 있다. 그는 스스로를 또래 여성과 끊임없이 비교하는 이들에게 메시지를 주고","link":"https://v.daum.net/v/20230720210031880","retrieved":1689855914967},{"title":"카일리 제너 \"가족마저 외모 지적...성형 수술 고민도\"","contents":"[TV리포트=이수연 기자] 카다시안 가족들이 외모에 대한 고민을 털어놨다. 20일(현지 시간) 공개된 'The Kardashians' 새 에피소드에서는 클로에 카다시안과 카일리 제너가 외모에 대한 불안감에 대해 털어놓는 장면이 담겨있었다. 카일리 제너는 언니들의 '영향력'과 '힘'이 다른 사람들의 미적 기준에 어떤 영향을 미쳤는지에 대해 말문을 꺼냈다. 그","link":"https://v.daum.net/v/20230720202030076","retrieved":1689855914969},{"title":"\"킴 카다시안 속옷 덕에 살았다\"...총격사고 생존자의 놀라운 증언","contents":"[TV리포트=이수연 기자] 할리우드 셀럽 킴 카다시안이 의도치 않게 한 여성의 생명을 구했다. 최근 한 여성은 자신의 소셜네트워크서비스를 통해 올해 초 4발의 총상을 입었으며 스킴스(SKIMS)에서 출시된 속옷인 보디슈트를 입어 죽지 않았다고 주장했다. 스킴스는 킴 카다시안이 설립한 속옷 브랜드다. 그는 \"내가 총에 맞았던 날, 드레스 안에 스킴스 보디슈","link":"https://v.daum.net/v/20230720194030279","retrieved":1689855914972},{"title":"'이혼' 아리아나 그란데, '위키드' 동료와 쇼핑 포착…미소띤 얼굴","contents":"[OSEN=김보라 기자]&nbsp;이혼을 결심한 가수 겸 배우 아리아나 그란데(30)가 동료 신시아 에리보(36)와 함께 있는 모습이 포착돼 관심을 끈다. 지난 18일(현지 시간) 아리아나 그란데는 새 뮤지컬영화 ‘위키드’에서 호흡을 맞춘 가수 겸 배우 신시아 에리보와 영국 런던의 본드 스트리트에서 목격됐다. 이날 아리아나 그란데는 선글라스와 모자로 얼굴을 가렸","link":"https://v.daum.net/v/20230720184620268","retrieved":1689848174117},{"title":"트래비스 스캇 신곡, 제목은 'KPOP'·커버는 '일장기'?...반응 분분","contents":"[OSEN=유수연 기자] 트래비스 스캇과&nbsp;위켄드, 베드 버니와 함께 콜라보 신곡을 발매하는 가운데, 발매 전부터 일부 누리꾼들의 갑론을박을 불러일으키고 있다. 오는 21일(현지시각) 힙합 뮤지션 트래비스 스콧이 라틴 팝을 대표하는 래퍼 배드 버니와&nbsp;뮤지션 위켄드와 콜라보한 신곡 'KPOP'을 발매한다. 다만 발매 전부터 'KPOP'의 앨범 표지가 누리꾼","link":"https://v.daum.net/v/20230720182119670","retrieved":1689848174121},{"title":"닉 조나스, 11살 연상 아내 생일 축하…\"누나 없이는 못 살아\"","contents":"[TV리포트=유비취 기자] 가수 닉 조나스가 11살 연상의 아내에 대한 애정을 공개적으로 표했다. 지난 18일 닉 조나스(30)는 소셜네트워크서비스를 통해 아내 프리앙카 초프라(41)의 생일을 축하했다. 그는 결혼한 지 5년이 됐어도 신혼과 같은 모습이었다. 닉 조나스는 \"당신을 축하해 주고 싶다. 생일 축하한다. 내 사랑\"이라는 달달한 글을 남겼다. 글","link":"https://v.daum.net/v/20230720180104926","retrieved":1689848174129},{"title":"돌프 룬드그렌, 암 투병 중 '38세 연하'와 결혼","contents":"[TV리포트=강성훈 기자] 스웨덴 액션 배우 돌프 룬드그렌(65)이 '38세 연하' 여자친구 엠마 크록덜(27)과 결혼했다. 돌프는 자신의 지난 12일 소셜네트워크서비스에 수영장에서 여자친구와 함께 찍은 사진을 올렸다. 사진과 함께 그는 \"내일이 그날이다\"라는 멘트를 덧붙였다.&nbsp; 돌프와 그의 여자친구가 약혼한 것은 2020년 6월이다. 그날 돌프는 왼손 약","link":"https://v.daum.net/v/20230720175400802","retrieved":1689848174129},{"title":"브리트니 스피어스, 신보서 '전성기 미모' 되찾았다","contents":"[TV리포트=이수연 기자] 올해 41세가 된 팝스타 브리트니 스피어스가 신보를 발매한다. 그룹 블랙 아이드 피스의 멤버 윌.아이.엠(will.i.am)는 19일 자신의 소셜네트워크서비스에 짧은 티저 영상을 공개하며 음반 발매에 대한 기대감을 높였다. 25초의 짧은 영상에는 우주가 연상되는 배경과 함께 웅장한 비트가 흘러나왔다. 또한 신곡 제목인 'Mind","link":"https://v.daum.net/v/20230720172930962","retrieved":1689848174132},{"title":"'우울증' 벨라 하디드, 위켄드 이어 현남친과 또 결별?","contents":"[OSEN=박소영 기자] 벨라 하디드와 마크 칼만이 결별설에 휩싸였다. 19일(현지시각) 외신 보도에 따르면 벨라 하디드는 2년 사귄 마크 칼만과 헤어졌다. 한 측근은 “그들은 몹시도 사랑에 빠졌지만 관계는 결국 끝났다. 벨라 하디드는 매우 좋은 사람이지만 이별 후 스스로를 돌보기 위해 노력하고 있다”고 밝혔다. 실제로 두 사람은 2021년 7월에 첫","link":"https://v.daum.net/v/20230720172219734","retrieved":1689848174135},{"title":"왕년의 스타, 인기 추락 후 '분식집'서 알바...팬들 응원 쏟아져","contents":"[TV리포트=안수현 기자] 홍콩 그룹 '보이즈' 출신인 장치향(스티븐 청)이 분식집에서 일하는 근황이 포착돼 팬들이 충격에 빠졌다. 장치향은 최근 몇 년 동안 여러 차례 연애 스캔들에 휘말린 후 명성이 추락했고, 연예 관련 활동도 끊겼다. 최근 한 네티즌은 그가 분식집에서 일하는 모습을 사진으로 찍어 소셜 네트워크 서비스에 공유했다. 장치향은 홍콩의 틴수","link":"https://v.daum.net/v/20230720172030629","retrieved":1689848174139},{"title":"성착취 논란 후폭풍? 쟈니스 소속, 배구월드컵 스페셜 서포터 불참","contents":"[뉴스엔 박수인 기자] 쟈니스 소속 아티스트들이 약 30년 만 배구 월드컵에 불참한다. 7월 19일 일본 매체 주간문춘은 쟈니스 사무소의 그룹이 약 30년에 걸쳐 배구 월드컵 스페셜 서포터를 맡아 왔으나 올해 대회에는 일절 출연하지 않는다고 보도했다. 1995년에는 V6, 1999년 아라시, 2003년 NEWS, 2007년 헤이세이점프, 2011년과 20","link":"https://v.daum.net/v/20230720162819580","retrieved":1689840932033},{"title":"기네스 팰트로, “여자가 백발하면 주름살과 피부노화 질문” 분노","contents":"[마이데일리 = 곽명동 기자]할리우드 배우 기네스 팰트로(50)가 자연스러운 늙음을 예찬하며 남녀간의 이중적인 기준에 일침을 놓았다. 그는 19일(현지시간) 영국 보그와 인터뷰에서 여성에게 가혹한 미의 기준에 불만을 토로했다. 팰트로는 \"여성으로서 우리는 건강해지고 싶고, 나이를 먹고 싶다\"면서 “우리가 시간에 갇혀 있어야 한다는 생각은 너무 이상하다","link":"https://v.daum.net/v/20230720161859206","retrieved":1689840932038},{"title":"'아쿠아맨' 65세 돌프 룬드그렌, 암투병 중 27세 여친과 결혼","contents":"&nbsp; [OSEN=최나영 기자] 65세의 할리우드 배우 돌프 룬드그렌이 암 투병 중&nbsp;그리스에서 27세의 여자친구 엠마 크록달과 결혼했다. 영화 '록키', '익스펜더블' 등으로&nbsp;유명하고 최근 '아쿠아맨', '크리드2' 등에 출연한 액션스타 룬드그렌이 암 투병 중인 가운데 13일 그리스에서 개인 트레이너인 27세 크록달과 결혼했다고 피플이&nbsp;19일(현지시간) 전","link":"https://v.daum.net/v/20230720160919772","retrieved":1689837234604},{"title":"제니퍼 로페즈, '2억' 패션으로 길거리 활보...가방만 '1억'짜리","contents":"[TV리포트=유비취 기자] 가수 겸 배우 제니퍼 로페즈가 약 1억 상당의 명품 가방을 들고 쇼핑에 나섰다. 지난 18일(현지 시간) 제니퍼 로페즈(53)는 미국 로스앤젤레스에서 쇼핑을 즐기는 모습이 포착됐다. 제니퍼 로페즈는 빨간색 드레스와 함께 빨간색 가방을 들어 시선을 끌었다. 그가 들고 있는 가방은 명품 브랜드 에르메스의 가방 중 하나인 버킨백이었다.","link":"https://v.daum.net/v/20230720160030355","retrieved":1689837234605}]}