{"title":"다음 연예 ─ 뉴스 ─ 스타","url":"https://entertain.daum.net/news/star","favicon":"https://entertain.daum.net/news/favicon.ico","elements":[{"title":"'2관왕' 이장우, '나혼산' 위해 ♥조혜원과 결혼 미룬 진정성","contents":"[OSEN=하수정 기자] 배우 이장우가 ‘2023 MBC 방송연예대상’에서 베스트 팀워크상과 리얼리티 최우수상을 수상하며 2023년을 뜻깊은 해로 장식했다. 이장우는 지난 29일 상암동 MBC 미디어센터에서 열린 ‘2023 MBC 방송연예대상’에서 베스트 팀워크상과 리얼리티 남자 최우수상을 수상하는 2관왕의 쾌거를 이뤘다. 2022년 MBC 대표 예능","link":"https://v.daum.net/v/20231230105025943","retrieved":1703901075608},{"title":"표예진, SBS 연기대상 우수 연기상 수상···눈부신 진가 재입증","contents":"배우 표예진이 ‘2023 SBS 연기대상’에서 수상의 영예를 안았다. 표예진이 지난 29일 개최된 ‘2023 SBS 연기대상’에서 시즌제 드라마 우수 연기상 여자 부문을 수상했다. 이를 통해 그는 탁월한 연기력은 물론, 배우로서 자신의 눈부신 진가를 재입증했다. 표예진은 2023년을 자신의 시간으로 알차게 채우며 ‘표예진의 해’로 만들었다. 올 상반","link":"https://v.daum.net/v/20231230103913841","retrieved":1703901075611},{"title":"‘대상’ 이제훈-김태리, 공동 수상","contents":"[동아닷컴]  ‘‘모범택시2’의 이제훈과 ‘악귀’의 김태리가 ‘2023 SBS 연기대상’에서 대상을 차지했다. 최고 시청률 25.6%를 돌파하며 ‘갓도기 신드롬’을 일으킨 ‘모범택시2’의 이제훈과 1인 2역의 '메소드 연기'로 평단과 대중의 찬사가 쏟아졌던 ‘악귀’의 김태리, 우열을 가릴 수 없는 연기를 보여준 두 배우가 대상의 수상을 안았다. 먼저 ‘","link":"https://v.daum.net/v/20231230103910840","retrieved":1703901075611},{"title":"이영애, 공연 준비 中 긴급 체포…'살인 협의' 차마에에 단원들 충격","contents":"[스포츠조선 이정혁 기자]이영애 연기 신공이 아까운 불륜에 혼외자 소동에 이번엔 살인 혐의까지 '마라맛 막장'이 이어진다. 누군가 마에스트라 이영애의 명예에 흠집을 내려는 시도가 포착됐다 . 30일 (토) 방송될 tvN 토일드라마 ' 마에스트라 '(극본 최이윤,연출 김정권,기획 스튜디오드래곤,제작 래몽래인·그룹에이트) 7회에서는 차세음 (이","link":"https://v.daum.net/v/20231230103907839","retrieved":1703901075615},{"title":"故이선균 추모, 선 넘는 애도 비판은 진행형…김이나→신현준 ‘삭제 릴레이’","contents":"[뉴스엔 이슬기 기자] 배우 신현준이 고(故) 배우 이선균의 추모글을 올렸다가 비판이 이어지자 삭제했다. 신현준은 12월 29일 소셜미디어에 서울 종로구의 한 공원을 방문한 사진을 올렸다. 별 다른 글이 더해지지 않은 게시글에는 술과 안주와 함께 꽃다발이 놓여 있는 풍경 만이 담겼다. 문제는 사진에 나오는 공터가 이씨가 숨진 채 발견된 공원 인근인 것으로","link":"https://v.daum.net/v/20231230103032755","retrieved":1703901075615},{"title":"D-day 'MBC 연기대상' 최후의 승자는?..대상만큼 치열한 '베커상'도 관심","contents":"[스포츠조선 조윤선 기자] 오늘(30일) 저녁 8시 40분, MBC를 빛낸 드라마 스타들의 축제가 열린다. 2023년 한 해 시청자들을 울리고 웃겼던 드라마 주인공들이 총출동하는 '2023 MBC 연기대상'이 오늘(30일) 개최된다. 사극부터 로맨틱 코미디, 활극까지 다채로운 장르의 작품들이 안방을 찾은 만큼 어느 때보다 화려한 별들의 잔치가","link":"https://v.daum.net/v/20231230102945733","retrieved":1703901075615},{"title":"故 이선균 추모의 장 '2023 SBS 연기대상', 축제는 없었다","contents":"[스포츠투데이 서지현 기자] '2023 SBS 연기대상'이 세상을 떠난 故 이선균을 추모하는 자리가 됐다. 축제의 장이자 연말의 꽃으로 불리는 시상식은 웃음과 박수 대신 동료 배우를 향한 애도로 채워졌다. 29일 저녁 서울 마포구 상암동 SBS 프리즘 타워에서 방송인 신동엽과 배우 김유정의 진행으로 '2023 SBS 연기대상'이 진행됐다. 이날 1부 축하","link":"https://v.daum.net/v/20231230102904723","retrieved":1703901075616},{"title":"기안84, 이변 없이 ‘MBC 연예대상’ 대상…‘태계일주’ 7관왕","contents":"이변은 없었다. 웹툰 작가 겸 방송인 기안84가 ‘2023 MBC 방송연예대상’ 대상을 차지했다. ‘2023 MBC 방송연예대상’이 지난 29일 오후 서울시 마포구 MBC 신사옥에서 개최됐다. 방송인 전현무, 덱스, 배우 이세영이 진행을 맡았다. 이날 영예의 대상은 기안84에게 돌아갔다. 기안84는 “아버지께 용돈 한 번 못 드렸다. 마지막까지 생활비","link":"https://v.daum.net/v/20231230102724707","retrieved":1703901075617},{"title":"상 쪼개고 나누고 없애고…'SBS 연기대상', 명분도 권위도 놓쳤다","contents":"[스포티비뉴스=장진리 기자] 'SBS 연기대상'이 지나친 상 나눠주기 인심으로 시청자들의 빈축을 샀다. 29일 방송된 '2023 SBS 연기대상'은 상 나눠먹기, 쪼개먹기로 권위 잃은 시상식의 표본을 보였다. SBS가 2023년 방송한 드라마는 '모범택시2', '악귀', '낭만닥터 김사부3', '트롤리', '소방서 옆 경찰서 그리고 국과수', '꽃선","link":"https://v.daum.net/v/20231230101005496","retrieved":1703901075617},{"title":"박나래는 왜 대상 후보에도 빠졌나? 'MBC 방송연예대상', 선정 기준 '논란'","contents":"[스포츠조선 이정혁 기자]수상부문은 엿장수 맘대로? 엿가락 늘리듯 자유자재(?) 후보와 부문 선정, 수상 기준을 놓고 갑론을박이 뜨겁다. 지난 29일 서울 마포구 상암동 MBC 공개홀에서 '2023 MBC 방송연예대상'이 생방송으로 진행됐다. 방송인 전현무, 덱스, 배우 이세영이 MC를 맡은 가운데, 대상 수상자로는 '나 혼자 산다', '","link":"https://v.daum.net/v/20231230100922485","retrieved":1703901075619},{"title":"기안84, 非예능인 대상→성소수자 풍자, 女신인상 '새 역사'","contents":"[스포티비뉴스=김현록 기자]비연예인 기안84가 최고 영예 대상을 수상했다. 트랜스젠더 방송인 풍자는 여자 신인상을 받았다. 29일 오후 '2023 MBC 방송연예대상' 시상식이 전현무 덱스 이세영의 사회로 열렸다. 이날 MBC 방송연예대상은 방송가의 새 역사를 썼다. 관심을 모은 대상은 이변없이 기안84의 차지였다. 이 가운데 트랜스젠더 방송인 풍자","link":"https://v.daum.net/v/20231230100603449","retrieved":1703901075620},{"title":"기안84, 비연예인 첫 대상까지 '나혼산' 8년➝'태계일주' 1년","contents":"[OSEN=선미경 기자] 확신의 대상감에서 진짜 대상의 주인공이 됐다. 최초의 비연예인 대상 수상자로 강렬하게 존재감을 각인시킨 기안84였다. 웹툰 작가 겸 화가 기안84가 결국은 해냈다. 확신의 대상감이라는 부담스러운 시선과 방송인 전현무의 견제를 견디로 대상 트로피를 품에 안았다. 그것도 쟁쟁한 유재석과 전현무 사이에서였다. 일찌감치 대상 수상자로","link":"https://v.daum.net/v/20231230100421425","retrieved":1703901075621},{"title":"정형돈♥한유라 “오래 매달려 잡은 사랑, 태연과 밤새 우결할 때도!”","contents":"[뉴스엔 이슬기 기자] 개그맨 정형돈이 사랑에 대해 이야기했다. 12월 29일 채널 오은영의 버킷리스트의 '은영이랑 밥 먹자' 콘텐츠에는 방송인 정형돈이 게스트로 출연했다. 이날 정형돈은 아내 한유라에 대해 이야기하면서 “만약 누나가 아니었다면 나는 지금도 애들이랑 데면데면했을 거 같다\"라고 해 시선을 끌었다. 그는 \"누나가 형님이랑 손을 딱 잡고 가는","link":"https://v.daum.net/v/20231230095940303","retrieved":1703901075623},{"title":"이장우, ♥조혜원에 \"결혼 미뤄도 될까?\"..'나혼산'에 진심인 '팜유 왕자'","contents":"[스포츠조선 조윤선 기자] 배우 이장우가 공개 연애 중인 연인 조혜원에게 사랑을 고백하면서 동시에 '나 혼자 산다'('이하 '나혼산')에 대한 진심을 드러냈다. 지난 29일 서울 마포구 상암동 MBC 신사옥에서는 '2023 MBC 방송연예대상'이 생방송으로 진행됐다. 이날 시상식은 전현무, 이세영, 덱스가 MC를 맡았다. '나혼산'에 출연 중","link":"https://v.daum.net/v/20231230095304246","retrieved":1703901075624},{"title":"'비연예인 최초' 기안84, 여혐·왕따 논란 딛고 대상 받기까지","contents":"[OSEN=하수정 기자] 웹툰 작가 겸 방송인 기안84가 '2023 MBC&nbsp;방송연예대상'에서 비연예인 최초로 단독 대상을 거머쥐었다. 천하의 유느님과 지난해 대상 수상자 전현무도 기안84의 기세를 막지 못했다.&nbsp; # 충격적인 첫 등장 '노병가' '패션왕' '복학왕' 등으로 유명한 웹툰 작가 기안84는 2016년 처음으로 '나혼자산다'에 등장했다. N포털","link":"https://v.daum.net/v/20231230095237235","retrieved":1703901075626}]}