{"title":"네이버 TV연예 ─ 최신뉴스 ─ 뮤직","url":"https://entertain.naver.com/now?sid=7a5","favicon":"https://entertain.naver.com/favicon.ico","elements":[{"title":"블랙핑크 고척돔 피날레..마지막 서울 공연 되는걸까[★FOCUS]","contents":"걸그룹 블랙핑크(BLACKPINK, 지수 로제 제니 리사)가 고척돔에서의 월드투어 피날레 이후 '마의 7년'을 넘어서서 YG와 계속 동행하게 될까. 블랙핑크는 16일과 17일 서울 고척 스카이돔에서 'BLACKPIN","link":"https://entertain.naver.com/now/read?oid=108&aid=0003181793","retrieved":1694819498368},{"title":"블랙핑크, 이번 주말 고척돔 공연…175만 월드투어 '본 핑크' 마무리","contents":"K팝 간판 걸그룹 '블랙핑크'가 11개월간 전 세계 34개 도시를 돌며 175만명을 끌어 모은 월드 투어 '본 핑크' 피날레를 서울에서 장식한다. 16일 소속사 YG엔터테인먼트에 따르면, 블랙핑크는 이날과 17일 서","link":"https://entertain.naver.com/now/read?oid=003&aid=0012093396","retrieved":1694819498370},{"title":"VVON(본) 새 싱글 ‘Time Out’ 발매···키드와인 지원사격","contents":"알앤비 아티스트 VVON(본)이 새 싱글로 돌아왔다. VVON은 15일 각종 온라인 음원사이트를 통해 새 싱글 ‘Time Out(타임 아웃) (Feat. Kid Wine)’을 발매했다. ‘Time Out (Feat.","link":"https://entertain.naver.com/now/read?oid=144&aid=0000913340","retrieved":1694819498371},{"title":"임영웅, '폴라로이드' 뮤직비디오 2000만뷰 돌파…역시 히어로!","contents":"가수 임영웅의 '폴라로이드(Polaroid)' 뮤직비디오가 2000만 뷰를 돌파했다. 지난해 11월 14일 임영웅 공식 유튜브 채널을 통해 공개된 임영웅의 '폴라로이드(Polaroid)' 뮤직비디오 조회수가 지난 1","link":"https://entertain.naver.com/now/read?oid=117&aid=0003771041","retrieved":1694819498373},{"title":"걸그룹 출신 BJ, 기획사 대표 성폭행 무고 혐의 재판 넘겨져","contents":"소속사 대표가 자신을 강간하려 했다며 허위 고소한 걸그룹 출신 인터넷 방송인 A씨가 기소됐다. 15일 뉴스1에 따르면, 서울중앙지검 여성아동범죄조사1부(부장검사 김은미)는 지난 7일 A(23)씨를 무고 혐의로 불구속","link":"https://entertain.naver.com/now/read?oid=003&aid=0012093394","retrieved":1694819498374},{"title":"방탄소년단 뷔 '슬로 댄싱', 英 싱글차트 24위 데뷔","contents":"글로벌 슈퍼 그룹 '방탄소년단'(BTS) 멤버 뷔(V·김태형)가 솔로로서 영국(UK) 오피셜 싱글차트 상위권에 진입했다. 15일(현지시간) 오피셜 차트에 따르면, 뷔가 지난 8일 공개한 첫 솔로 앨범 '레이오버(La","link":"https://entertain.naver.com/now/read?oid=003&aid=0012093391","retrieved":1694819498375},{"title":"저스트비, 데뷔 후 첫 완전체 OST 참여···‘사장돌마트’ OST ‘Paradise’ 발매","contents":"아이돌그룹 저스트비(JUST B)가 첫 완전체 OST를 선보였다. 15일 저스트비(임지민, 이건우, 배인, JM, 전도염, 김상우)가 완전체로 참여한 티빙 오리지널 시리즈 ‘사장돌마트’ OST Part.2 ‘Para","link":"https://entertain.naver.com/now/read?oid=144&aid=0000913337","retrieved":1694819498376},{"title":"다이나믹 듀오 혼 쏙 뺀 방탄소년단 정국 'Smoke' 챌린지, 14시간 만 2000만뷰 돌파..칼박+칼각 '극강 파워풀 댄스'","contents":"방탄소년단(BTS) 정국의 'Smoke(스모크)' 챌린지가 공개 14시간 만에 조회수 2000만을 넘어서며 폭발적인 인기를 보여줬다. 정국은 지난 15일 팬 커뮤니티 위버스와 자신의 틱톡 계정을 통해 \"나도 함 해본","link":"https://entertain.naver.com/now/read?oid=108&aid=0003181785","retrieved":1694819498377},{"title":"가을 정취 물씬~♡ 이찬원, '제10회 에코-랜드 가을음악회' 출연","contents":"가수 이찬원이 경기도 남양주에서 팬들과 만난다. 이찬원은 16일 오후 5시 경기도 남양주시 청학로 에코-랜드 축구장 특설무대에서 열리는 '제10회 에코-랜드 가을음악회'에 출연해 무대를 꾸민다. 코로나19로 지친 주","link":"https://entertain.naver.com/now/read?oid=108&aid=0003181784","retrieved":1694819498378},{"title":"'라디오 킹' 방탄소년단 진 '디 애스트로넛' 아르헨티나 베가 라디오 46주간 1위","contents":"방탄소년단(BTS) 진의 '디 애스트로넛'(The Astronaut)이 아르헨티나(Argentine) 인기 라디오 채널에서 1위를 차지하며 독보적인 인기를 과시했다. 진의 첫 솔로 싱글 '디 애스트로넛'은 지난 9월","link":"https://entertain.naver.com/now/read?oid=108&aid=0003181783","retrieved":1694819498379},{"title":"'트롯돌' 이찬원, 아이돌차트 평점랭킹 83주 연속 TOP2","contents":"가수 이찬원이 아이돌차트 평점랭킹에서 83주 연속 톱 2를 기록하며 인기를 빛냈다. 이찬원은 9월 2주차 아이돌차트 평점랭킹에서 26만 4621표를 획득, 전체 2위를 차지했다. 이찬원은 이로써 83주 연속 평점랭킹","link":"https://entertain.naver.com/now/read?oid=108&aid=0003181782","retrieved":1694819498380},{"title":"'찬또배기' 이찬원, 한밤 중 라이브 방송으로 전한 팬 사랑","contents":"이찬원이 한 밤 중에 라이브 방송을 통해 팬들에게 감사와 사랑을 전했다. 최근 이찬원은 자신의 공식 계정을 통해 라이브 방송을 진행했다. 당시, 경남 창녕에서 열린 '제6회 창녕양파가요제'에 초대가수로 출격해 엔딩","link":"https://entertain.naver.com/now/read?oid=311&aid=0001639230","retrieved":1694819498381},{"title":"뱀뱀, 키 옛날 집에서 술 마시다가 필름 끊겨 “일어나 보니 팬티만 입고..”","contents":"출처 | 유튜브 ‘뱀집’ 그룹 샤이니 키와 갓세븐 뱀뱀이 친분을 드러냈다. 15일 유튜브 채널 ‘뱀집’에는 ‘[SUB]뱀이에겐 너무 멋진 Good &amp; Great 키 슨배님이거든요~(ENG/TH)Ep.2’라는 영상이","link":"https://entertain.naver.com/now/read?oid=468&aid=0000980908","retrieved":1694819498381},{"title":"'감성 No.1' 임영웅 '폴라로이드' MV 2000만뷰","contents":"가수 임영웅의 'Polaroid'(폴라로이드) 뮤직비디오가 2000만 뷰를 달성했다. 지난해 11월 14일 임영웅 공식 유튜브 채널을 통해 선공개된 '폴라로이드' 뮤직비디오는 9월 15일 조회수 2000만 뷰를 넘어","link":"https://entertain.naver.com/now/read?oid=108&aid=0003181780","retrieved":1694812519489},{"title":"블랙핑크, 이번 주말 서울서 월드투어 대장정 마무리","contents":"주말 양일간 고척스카이돔…17일 공연은 온라인 생중계도 걸그룹 블랙핑크가 16∼17일 서울 고척스카이돔서 월드투어 '본 핑크'(BORN PINK)의 대미를 장식하는 앙코르 피날레 공연을 연다. 16일 소속사 YG엔터","link":"https://entertain.naver.com/now/read?oid=001&aid=0014196635","retrieved":1694812519490},{"title":"블랙핑크 제니, 강렬 의상도 완벽 소화..역시 화보장인","contents":"그룹 블랙핑크의 멤버 제니가 화보 장인 포스를 자랑했다. 15일 패션매거진 하퍼스 바자 측은 공식 채널을 통해 \"지금 이 순간, 더없이 눈부신 제니\"라며 커버 사진을 공개했다. 이어 \"2023년 세계에서 가장 영향력","link":"https://entertain.naver.com/now/read?oid=112&aid=0003653756","retrieved":1694812519491},{"title":"HK직캠｜허영지, 커다란 하트 풍선 들고 등장… '오늘도 예쁜 미소' (뮤직뱅크 출근길)","contents":"가수 허영지가 15일 오전 서울 여의도 KBS 신관 공개홀에서 열린 '뮤직뱅크' 리허설에 참석해 포즈를 취하고 있다.","link":"https://entertain.naver.com/now/read?oid=015&aid=0004892581","retrieved":1694790742037},{"title":"HK직캠｜하이키 휘서, 핑크로 상큼하게… '러블리한 미소에 시선강탈' (뮤직뱅크 출근길)","contents":"그룹 하이키 휘서가 15일 오전 서울 여의도 KBS 신관 공개홀에서 열린 '뮤직뱅크' 리허설에 참석해 포즈를 취하고 있다.","link":"https://entertain.naver.com/now/read?oid=015&aid=0004892580","retrieved":1694790742040},{"title":"HK직캠｜퍼플키스 나고은, 눈 뗄 수 없는 깜찍함… '귀여운 고양이 같아~' (뮤직뱅크 출근길)","contents":"그룹 퍼플키스 나고은이 15일 오전 서울 여의도 KBS 신관 공개홀에서 열린 '뮤직뱅크' 리허설에 참석해 포즈를 취하고 있다.","link":"https://entertain.naver.com/now/read?oid=015&aid=0004892579","retrieved":1694790742042},{"title":"HK직캠｜파우 요치, '만화 속 주인공 같은 꽃미남 선배 비주얼' (뮤직뱅크 출근길)","contents":"그룹 파우 요치가 15일 오전 서울 여의도 KBS 신관 공개홀에서 열린 '뮤직뱅크' 리허설에 참석해 포즈를 취하고 있다.","link":"https://entertain.naver.com/now/read?oid=015&aid=0004892578","retrieved":1694790742042},{"title":"HK직캠｜트렌드지 한국, 멋진 모습으로 등장… '밝게 웃는 미소에 심쿵' (뮤직뱅크 출근길)","contents":"그룹 트렌드지 한국이 15일 오전 서울 여의도 KBS 신관 공개홀에서 열린 '뮤직뱅크' 리허설에 참석해 포즈를 취하고 있다.","link":"https://entertain.naver.com/now/read?oid=015&aid=0004892576","retrieved":1694790742043},{"title":"HK직캠｜크래비티 성민, 금발로 멋지게… '마스크를 써도 멋진 남자' (뮤직뱅크 출근길)","contents":"그룹 크래비티 성민이 15일 오전 서울 여의도 KBS 신관 공개홀에서 열린 '뮤직뱅크' 리허설에 참석해 포즈를 취하고 있다.","link":"https://entertain.naver.com/now/read?oid=015&aid=0004892575","retrieved":1694790742045},{"title":"HK직캠｜이채연, 선글라스 쓰고 도도하게… '감출 수 없는 댄스 본능' (뮤직뱅크 출근길)","contents":"가수 이채연이 15일 오전 서울 여의도 KBS 신관 공개홀에서 열린 '뮤직뱅크' 리허설에 참석해 포즈를 취하고 있다.","link":"https://entertain.naver.com/now/read?oid=015&aid=0004892574","retrieved":1694790742047},{"title":"HK직캠｜신현희, '엉망진창' 아닌 상큼함 가득한 모습 (뮤직뱅크 출근길)","contents":"가수 신현희가 15일 오전 서울 여의도 KBS 신관 공개홀에서 열린 '뮤직뱅크' 리허설에 참석해 포즈를 취하고 있다.","link":"https://entertain.naver.com/now/read?oid=015&aid=0004892573","retrieved":1694787206647},{"title":"HK직캠｜보이넥스트도어 운학, '우산 들어주는 든든한 오빠 같은 막내' (뮤직뱅크 출근길)","contents":"그룹 보이넥스트도어 운학이 15일 오전 서울 여의도 KBS 신관 공개홀에서 열린 '뮤직뱅크' 리허설에 참석해 포즈를 취하고 있다.","link":"https://entertain.naver.com/now/read?oid=015&aid=0004892572","retrieved":1694787206653}]}