{"title":"네이버 TV연예 ─ 최신뉴스 ─ 연예가화제","url":"https://entertain.naver.com/now?sid=221","favicon":"https://entertain.naver.com/favicon.ico","elements":[{"title":"탕웨이♥김태용 감독, 결혼 10주년 노을 아래 단란한 세 가족","contents":"중국 배우 탕웨이와 김태용 감독이 딸과 함께 가족만의 오붓한 시간을 보냈다. 탕웨이는 12일 \"서호의 강을 떠올리며, 10년\"이라는 글과 함께 사진을 올렸다. 공개된 사진 속에는 노을 아래 서 있는 김태용 감독과 탕","link":"https://m.entertain.naver.com/now/article/421/0007660674","retrieved":1720832371367},{"title":"장영란, 무명설움 고백 \"무시·천대받고 오열..매니저·경호원한테 맞기도\"(A급장영란)","contents":"방송인 장영란이 신인 시절 설움을 고백했다. 12일 공개된 채널 'A급 장영란'에는 '20년 전 매일 숨어서 울었던 장영란 눈물의 장소는? (성공스토리)'라는 제목의 영상이 게재됐다. 영상 속 장영란은 목동에 위치한","link":"https://m.entertain.naver.com/now/article/076/0004168273","retrieved":1720832371367},{"title":"팔콘의 변신…'캡틴 아메리카: 브레이브 뉴 월드', 내년 2월 개봉","contents":"영화 '캡틴 아메리카: 브레이브 뉴 월드'(감독 줄리어스 오나)가 2025년 2월 개봉을 확정했다. 월트디즈니 컴퍼니 코리아는 13일 이같이 밝히며 '캡틴 아메리카: 브레이브 뉴 월드'의 티저 포스터와 예고편을 공개","link":"https://m.entertain.naver.com/now/article/421/0007660673","retrieved":1720832371368},{"title":"'혀열 진단' 안재현 \"매우 나쁨은 아니네”→오리 먹방 (나혼산)","contents":"‘나 혼자 산다’에서 안재현이 무더운 여름 나기를 위해 자신의 건강 상태를 체크하고 맞춤 보양식으로 원기를 충전했다. 건강의 문제점을 발견한 후 오히려 긍정적인 생각으로 몸과 정신을 재정비하는 안재현. 그의 다음 이","link":"https://m.entertain.naver.com/now/article/382/0001137993","retrieved":1720832371369},{"title":"[차트IS] 장나라 ‘굿파트너’, 7.8%로 출발…’단짠’ 로펌 생존기 출발","contents":"SBS 새 금토드라마 ‘굿파트너’가 7%대 시청률로 출발했다. 13일 시청률조사기관 닐슨코리아에 따르면 지난 12일 방송된 ‘굿파트너’ 1회는 전국 기준 7.8%를 기록했다. 이는 전작 ‘커넥션’ 5.7%보다 2.1","link":"https://m.entertain.naver.com/now/article/241/0003364946","retrieved":1720832371373},{"title":"아파도 언제나 밝은 쯔양… 박명수와 통화했다","contents":"남몰래 힘든 시간을 보냈던 먹방 유튜버 쯔양(본명 박정원)이 개그맨 박명수의 유튜브 채널 '할명수'에 등장했다. 쯔양이 박명수의 유튜브 채널에 등장한 건 전 남친이자 소속사 대표였던 A씨와의 힘든 시간을 고백하기 전","link":"https://m.entertain.naver.com/now/article/417/0001014166","retrieved":1720832371374},{"title":"[가요소식] 스키즈 '칙칙붐' 뮤비 티저에 라이언 레이놀즈 출연","contents":"시가렛 애프터 섹스, 5년 만에 정규앨범·그리프, 정규 1집 '버티고' ▲ 스트레이 키즈 '칙칙붐' 티저 공개 = 그룹 스트레이 키즈가 할리우드 배우 라이언 레이놀즈가 출연한 신곡 '칙칙붐'(Chk Chk Boom)","link":"https://m.entertain.naver.com/now/article/001/0014804619","retrieved":1720832371376},{"title":"“직원만 400명” 염혜란, 세계 최대 훠궈 식당 지배인 됐다 (‘가브리엘’)","contents":"JTBC 예능프로그램 ‘마이 네임 이즈 가브리엘’(‘My name is 가브리엘’, 이하 ‘가브리엘’)이 새로운 가브리엘 염혜란의 등장과 함께 역대급 스케일의 훠궈 식당으로 시선을 사로잡았다. 지난 12일 방송된 ‘","link":"https://m.entertain.naver.com/now/article/241/0003364944","retrieved":1720832371377},{"title":"구제역 \"쯔양 소속사에 돈 받았다…빠른 시일 내 돌려드릴 것\"","contents":"유튜버 구제역이 쯔양 협박 의혹과 관련한 입장을 밝혔다. 구제역은 지난 12일 유튜브 채널 커뮤니티에 '쯔양에게 사과드린다. 지난해 2월 쯔양의 전 소속사 대표로 추정되는 자에게 쯔양에 대한 익명 제보를 받은 사실이","link":"https://m.entertain.naver.com/now/article/437/0000401372","retrieved":1720832371379},{"title":"[TVis] 벤, 이혼 언급 “한번 다녀왔고 17개월 딸 육아” (‘더 시즌즈’)","contents":"가수 벤이 이혼 후 처음으로 무대에 올랐다. 벤은 지난 12일 방송된 KBS2 ‘더 시즌즈-지코의 아티스트’(이하 ‘더 시즌즈’) 에 게스트로 출연했다. 벤은 “데뷔 후 이렇게 오래 쉬어본 적이 거의 처음이다. 2년","link":"https://m.entertain.naver.com/now/article/241/0003364943","retrieved":1720832371381},{"title":"'낮밤녀' 정은지·최진혁, 취중 입맞춤 시도 후 흐르는 묘한 기류","contents":"배우 정은지와 최진혁이 취중 입맞춤 시도 후유증에 시달릴 예정이다. 13일 방송될 JTBC '낮과 밤이 다른 그녀'(이하 '낮밤녀') 9회에서는 술김에 계지웅(최진혁)의 입술로 돌진한 이미진(정은지)이 또 하나의 흑","link":"https://m.entertain.naver.com/now/article/437/0000401371","retrieved":1720832371382},{"title":"그림 같은 이 미모가 53세 이영애","contents":"배우 이영애가 팬들에게 일상을 공개하며 기품 넘치는 미모를 자랑했다. 이영애는 13일 자신의 인스타그램에 \"사임당과 오순경 작가님, 다시 만나니 너무 반가웠어요, 사임담빛의일기, 오순경 작가, 아트팩토리참기름\"이라는","link":"https://m.entertain.naver.com/now/article/417/0001014165","retrieved":1720832371384},{"title":"이효리 모녀 첫 듀엣곡 ‘섬집 아기’ OST 나온다(by ♥이상순)","contents":"이상순이 이효리와 장모님을 위해 디렉터로 나선다. 14일(일) 밤 9시 10분에 방송되는 JTBC '엄마, 단둘이 여행 갈래?' 최종회는 이효리 모녀의 첫 듀엣곡 녹음 현장과 여행 비하인드로 꾸며진다. 이효리는 여행","link":"https://m.entertain.naver.com/now/article/076/0004168270","retrieved":1720832371385},{"title":"벤, '쿨'한 이혼 언급 \"한 번 갔다와…17개월 딸 리아 육아\"","contents":"가수 벤이 쿨하게 이혼을 언급했다. 벤은 지난 12일 방송된 KBS 2TV '더 시즌즈-지코의 아티스트'에 출연해 2년 3개월 만에 복귀한 소감을 알렸다. 이날 벤은 '또 오해영'의 OST였던 '꿈처럼'을 부르며 등","link":"https://m.entertain.naver.com/now/article/421/0007660643","retrieved":1720832371387},{"title":"탕웨이♥김태용 감독, 결혼 10주년…딸 썸머와 가족사진","contents":"배우 탕웨이가 김태용 감독과의 결혼 10주년을 기념했다. 탕웨이는 12일 자신의 SNS에 “서호의 연꽃을 생각하며 10년♥(念起西湖里的荷 10年♥)”이라는 글을 올렸다. 이와 함께 탕웨이는 가족과 즐거운 시간을 보내","link":"https://m.entertain.naver.com/now/article/241/0003364942","retrieved":1720832371388},{"title":"\"그러면 어떡해요 형님\" 이서진, 분할결제 늪에 빠졌다 (서진이네2)","contents":"‘서진이네2’ 정유미가 주방에 평화를 가져왔다. 지난 12일 방송된 tvN ‘서진이네2(연출 나영석, 박현용)’ 3회에서는 헤드 셰프 정유미의 진두지휘 아래 두 번째 영업에 돌입한 서진뚝배기의 에피소드가 공개됐다.","link":"https://m.entertain.naver.com/now/article/382/0001137991","retrieved":1720832371389},{"title":"서장훈 \"100m 달리기=12초\" 역시 국보급 센터(아는 형님)","contents":"형님들의 사이판 수학여행 둘째 날이 공개된다. 13일(토) 방송되는 JTBC '아는 형님'에서는 사이판으로 해외 수학여행을 떠난 형님들의 둘째 날이 공개된다. 이날 방송에서는 사이판의 아름다운 바다와 시원한 해변 게","link":"https://m.entertain.naver.com/now/article/076/0004168269","retrieved":1720832371391},{"title":"[차트IS] ‘서진이네2’, 또 자체최고 9.1%...베테랑 셰프 정유미 활약","contents":"tvN 예능프로그램 ‘서진이네2’가 또 자체 최고 시청률을 기록했다. 13일 시청률조사기관 닐슨코리아에 따르면 지난 12일 방송된 ‘서진이네2’ 3회는 전국 유료가구 기준 9.1%를 기록했다. 이는 지난 2회 8.1","link":"https://m.entertain.naver.com/now/article/241/0003364940","retrieved":1720832371392},{"title":"\"돈 안 받았다더니\" 구제역, 결국 쯔양에 공개사과→여론 '싸늘'[전문]","contents":"\"쯔양 과거 지키려 후원금 받아, 전액 돌려드리겠다\" 구독자 1030만명 유튜버 쯔양의 과거를 빌미로 협박해 수천만원을 갈취한 의혹을 받고 있는 유튜버 구제역이 해명 영상과 함께 사과문을 게재했다. 12일 구제역은","link":"https://m.entertain.naver.com/now/article/076/0004168268","retrieved":1720832371394},{"title":"'엘리멘탈' 넘었다…'인사이드 아웃2' 역대 픽사 애니 흥행 1위","contents":"국내 개봉 역대 픽사 애니메이션 흥행 1위에 올랐다. 영화진흥위원회 영화관입장권통합전산망에 따르면 '인사이드 아웃 2(켈시 만 감독)'는 13일 오전 7시 누적 관객 수 730만7224명을 달성했다. 특히 이번 성적","link":"https://m.entertain.naver.com/now/article/437/0000401370","retrieved":1720832371395},{"title":"박명수, 논란 전 밝은 목소리 쯔양과 통화…\"편집 無, 감동\"","contents":"박명수가 웹예능 '할명수'에서 유튜버 쯔양과 통화를 했다. 지난 12일 유튜브 채널 '할명수'의 '냉면 아저씨의 여름 한정 연례행사 비빔냉면 투어 다녀왔습니다 | 할명수 ep.191'라는 제목의 에피소드에서 쯔양과","link":"https://m.entertain.naver.com/now/article/421/0007660633","retrieved":1720832371396},{"title":"설민석, 표절논란 후 3년만 복귀...“공포스러웠다”(강연자들)","contents":"석사 논문 표절 논란으로 활동을 중단했던 설민석이 ‘강연자들’을 통해 3년 만에 대중 앞에 섰다. 12일 MBC ‘심장을 울려라 강연자들’(이하 ‘강연자들’)이 첫 방송됐다. 이날의 강연 주제는 ‘한계’였던 가운데","link":"https://m.entertain.naver.com/now/article/009/0005334008","retrieved":1720832371398},{"title":"탕웨이, ♥김태용과 결혼 10주년 자축..딸 썸머와 함께 '단란'","contents":"배우 탕웨이가 김태용 감독과 결혼 10주년을 자축했다. 탕웨이는 12일 자신의 인스타그램에 \"서호의 강을 떠올리며 10년\"이라는 글과 함께 여러 장의 사진을 공개했다. 공개된 사진 속에는 8세 딸과 즐거운 한때를 보","link":"https://m.entertain.naver.com/now/article/108/0003250116","retrieved":1720832371400},{"title":"이태곤, KBS 아나운서와 핑크빛 기류 \"잊지못하는 전여친 2명\"('살림남')","contents":"이태곤이 폭탄발언으로 모두를 놀라게 했다. 13일 방송되는 KBS 2TV '살림하는 남자들 시즌2'(이하 '살림남')에서는 이태곤이 라디오 스페셜 DJ로 변신한다. 이날 이태곤은 평소 로망이었던 '황정민의 뮤직쇼'의","link":"https://m.entertain.naver.com/now/article/076/0004168267","retrieved":1720832371401},{"title":"크리스 존슨, ‘첫사랑 그녀’와 여행 중 돌발 상황…무슨 일? (패밀리가 왔다)","contents":"'한국인을 웃기는 외국인' 크리스 존슨과 '미국 패밀리'가 서울 명소를 탐방한다. 13일(오늘) 저녁 7시 50분 방송되는 대환장 한국 체험기 SBS Plus '패밀리가 왔다'에서는 지난주 'K-뷰티 데이'에 이어","link":"https://m.entertain.naver.com/now/article/382/0001137989","retrieved":1720832371403}]}